Workbook

Sheet Artists
A1: ConstituentID | B1: DisplayName | C1: ArtistBio | D1: Nationality | E1: Gender | F1: BeginDate | G1: EndDate
A2: 11 | B2: Jean (Hans) Arp | C2: French, born Germany (Alsace). 1886–1966 | D2: French | E2: male | F2: 1886 | G2: 1966
A3: 19 | B3: Richard Artschwager | C3: American, 1923–2013 | D3: American | E3: male | F3: 1923 | G3: 2013
A4: 34 | B4: Alvar Aalto | C4: Finnish, 1898–1976 | D4: Finnish | E4: male | F4: 1898 | G4: 1976
A5: 38 | B5: Magdalena Abakanowicz | C5: Polish, 1930–2017 | D5: Polish | E5: female | F5: 1930 | G5: 2017
A6: 60 | B6: Ansel Adams | C6: American, 1902–1984 | D6: American | E6: male | F6: 1902 | G6: 1984
A7: 94 | B7: Munira Al-Kazi | C7: Kuwaiti, born 1939 | D7: Kuwaiti | E7: female | F7: 1939 | G7: 0
A8: 140 | B8: Jim Amaral | C8: American, born 1933 | D8: American | E8: male | F8: 1933 | G8: 0
A9: 144 | B9: Woody van Amen | C9: Dutch, born 1936 | D9: Dutch | E9: male | F9: 1936 | G9: 0
A10: 153 | B10: Emma Amos | C10: American, 1937–2020 | D10: American | E10: female | F10: 1937 | G10: 2020
A11: 159 | B11: Gunnar Aagaard Andersen | C11: Danish, 1919–1982 | D11: Danish | E11: male | F11: 1919 | G11: 1982
A12: 208 | B12: Diane Arbus | C12: American, 1923–1971 | D12: American | E12: female | F12: 1923 | G12: 1971
A13: 229 | B13: Eugène Atget | C13: French, 1857–1927 | D13: French | E13: male | F13: 1857 | G13: 1927
... A60: 1247 | B60: Joseph Cornell | C60: American, 1903–1972 | D60: American | E60: male | F60: 1903 | G60: 1972
A61: 1249 | B61: Corning Glass Works, Corning, NY | C61: est. 1851 | D61: American | F61: 1851 | G61: 0
A62: 1300 | B62: Robert Creeley | C62: American, 1926–2005 | D62: American | E62: male | F62: 1926 | G62: 2005
A63: 1330 | B63: Robert Cumming | C63: American, 1943–2021 | D63: American | E63: male | F63: 1943 | G63: 2021
A64: 1332 | B64: Imogen Cunningham | C64: American, 1883–1976 | D64: American | E64: female | F64: 1883 | G64: 1976
A65: 1364 | B65: Salvador Dalí | C65: Spanish, 1904–1989 | D65: Spanish | E65: male | F65: 1904 | G65: 1989
A66: 1391 | B66: Sandu Darie | C66: Cuban, born Romania. 1908–1991 | D66: Cuban | E66: male | F66: 1908 | G66: 1991
A67: 1402 | B67: Arthur B. Davies | C67: American, 1862–1928 | D67: American | E67: male | F67: 1862 | G67: 1928
A68: 1422 | B68: Roy DeCarava | C68: American, 1919–2009 | D68: American | E68: male | F68: 1919 | G68: 2009
A69: 1438 | B69: Jonathan De Pas | C69: Italian, 1932–1991 | D69: Italian | E69: male | F69: 1932 | G69: 1991
A70: 1444 | B70: Niki de Saint Phalle | C70: French and American, 1930–2002 | D70: French | E70: female | F70: 1930 | G70: 2002
A71: 1467 | B71: Dorothy Dehner | C71: American, 1901–1994 | D71: American | E71: female | F71: 1901 | G71: 1994
A72: 1475 | B72: Jack Delano | C72: American, born Russia. 1914–1997 | D72: American | E72: male | F72: 1914 | G72: 1997
A73: 1479 | B73: Robert Delaunay | C73: French, 1885–1941 | D73: French | E73: male | F73: 1885 | G73: 1941
... A281: 5702 | B281: Michelle Stuart | C281: American, born 1938 | D281: American | E281: female | F281: 1938 | G281: 0
A282: 5707 | B282: Studio Opi | C282: Italian, established 1955 | D282: Italian | F282: 1955 | G282: 0
A283: 5719 | B283: Kumi Sugaï | C283: Japanese, 1919–1996 | D283: Japanese | E283: male | F283: 1919 | G283: 1996
A284: 5723 | B284: Louis Sullivan | C284: American, 1856–1924 | D284: American | E284: male | F284: 1856 | G284: 1924
A285: 5749 | B285: Luke Swank | C285: American, 1890–1944 | D285: American | E285: male | F285: 1890 | G285: 1944
A286: 5777 | B286: Sophie Taeuber-Arp | C286: French, born Switzerland. 1889–1943 | D286: Swiss | E286: female | F286: 1889 | G286: 1943
A287: 5799 | B287: Atsuko Tanaka | C287: Japanese, 1932–2005 | D287: Japanese | E287: female | F287: 1932 | G287: 2005
A288: 5806 | B288: Dorothea Tanning | C288: American, 1910–2012 | D288: American | E288: female | F288: 1910 | G288: 2012
A289: 5809 | B289: Antoni Tàpies | C289: Spanish, 1923–2012 | D289: Spanish | E289: male | F289: 1923 | G289: 2012
A290: 5814 | B290: Lenore Tawney | C290: American, 1907–2007 | D290: American | E290: female | F290: 1907 | G290: 2007
A291: 5858 | B291: Bob Thompson | C291: American, 1937–1966 | D291: American | E291: male | F291: 1937 | G291: 1966
A292: 5882 | B292: Jean Tinguely | C292: Swiss, 1925–1991 | D292: Swiss | E292: male | F292: 1925 | G292: 1991
A293: 5907 | B293: Joaquín Torres-García | C293: Uruguayan, 1874–1949 | D293: Uruguayan | E293: male | F293: 1874 | G293: 1949
A294: 5933 | B294: Rosemarie Trockel | C294: German, born 1952 | D294: German | E294: female | F294: 1952 | G294: 0
... A297: 5988 | B297: Cy Twombly | C297: American, 1928–2011 | D297: American | E297: male | F297: 1928 | G297: 2011
A298: 6011 | B298: Unidentified Designer | F298: 0 | G298: 0
A299: 6091 | B299: Georges Vantongerloo | C299: Belgian, 1886–1965 | D299: Belgian | E299: male | F299: 1886 | G299: 1965
A300: 6155 | B300: Massimo Vignelli | C300: Italian, 1931–2014 | D300: Italian | E300: male | F300: 1931 | G300: 2014
A301: 6165 | B301: Jacques Villon | C301: French, 1875–1963 | D301: French | E301: male | F301: 1875 | G301: 1963
A302: 6191 | B302: Wolf Vostell | C302: German, 1932–1998 | D302: German | E302: male | F302: 1932 | G302: 1998
A303: 6194 | B303: Édouard Vuillard | C303: French, 1868–1940 | D303: French | E303: male | F303: 1868 | G303: 1940
A304: 6208 | B304: Wilhelm Wagenfeld | C304: German, 1900–1990 | D304: German | E304: male | F304: 1900 | G304: 1990
A305: 6210 | B305: Otto Wagner | C305: Austrian, 1841–1918 | D305: Austrian | E305: male | F305: 1841 | G305: 1918
A306: 6246 | B306: Andy Warhol | C306: American, 1928–1987 | D306: American | E306: male | F306: 1928 | G306: 1987
A307: 6275 | B307: Max Weber | C307: American, born Russia. 1881–1961 | D307: American | E307: male | F307: 1881 | G307: 1961
A308: 6282 | B308: Hans Wegner | C308: Danish, 1914–2007 | D308: Danish | E308: male | F308: 1914 | G308: 2007
A309: 6329 | B309: Edward Weston | C309: American, 1886–1958 | D309: American | E309: male | F309: 1886 | G309: 1958
A310: 6356 | B310: Metall-Arbeit Wiener Werkstätte | C310: Austrian | D310: Austrian | F310: 0 | G310: 0
A311: 6394 | B311: Sven Wingquist | C311: Swedish, 1876–1953 | D311: Swedish | E311: male | F311: 1876 | G311: 1953
A312: 6402 | B312: Jackie Winsor | C312: American, born Canada. 1941-2024 | D312: American | E312: female | F312: 1941 | G312: 2024
A313: 6459 | B313: Frank Lloyd Wright | C313: American, 1867–1959 | D313: American | E313: male | F313: 1867 | G313: 1959
A314: 6476 | B314: Ahmed Yacoubi | C314: Moroccan and American, 1928–1985 | D314: Moroccan | E314: male | F314: 1928 | G314: 1985
A315: 6518 | B315: Arthur Young | C315: American, 1905–1995 | D315: American | E315: male | F315: 1905 | G315: 1995
A316: 6520 | B316: La Monte Young | C316: American, born 1935 | D316: American | E316: male | F316: 1935 | G316: 0
A317: 6524 | B317: Jack Youngerman | C317: American, 1926–2020 | D317: American | E317: male | F317: 1926 | G317: 2020
A318: 6533 | B318: Ossip Zadkine | C318: French, born Russia. 1890–1967 | D318: French | E318: male | F318: 1890 | G318: 1967
A319: 6543 | B319: Michael S. Zane | C319: American, born 1948 | D319: American | E319: male | F319: 1948 | G319: 0
A320: 6602 | B320: Lorna Simpson | C320: American, born 1960 | D320: American | E320: female | F320: 1960 | G320: 0
A321: 6623 | B321: David Wojnarowicz | C321: American, 1954–1992 | D321: American | E321: male | F321: 1954 | G321: 1992
A322: 6624 | B322: Fernand Léger | C322: French, 1881–1955 | D322: French | E322: male | F322: 1881 | G322: 1955
... A366: 8324 | B366: John Van Hamersveld | C366: American, born 1941 | D366: American | E366: male | F366: 1941 | G366: 0
A367: 8412 | B367: Haus-Rucker-Co | C367: Austrian, est. 1967–1992 | D367: Austrian | F367: 1967 | G367: 1992
A368: 8413 | B368: Günter Zamp Kelp | C368: Austrian, born 1941 | D368: Austrian | E368: male | F368: 1941 | G368: 0
A369: 8414 | B369: Klaus Pinter | C369: Austrian, born 1940 | D369: Austrian | E369: male | F369: 1940 | G369: 0
A370: 8418 | B370: Philippe Starck | C370: French, born 1949 | D370: French | E370: male | F370: 1949 | G370: 0
A371: 8435 | B371: Gerald Summers | C371: British, 1899–1967 | D371: British | E371: male | F371: 1899 | G371: 1967
A372: 8492 | B372: Taylor Mead | C372: American, 1924 – 2013 | D372: American | E372: male | F372: 1924 | G372: 2013
A373: 8595 | B373: Unidentified photographer | F373: 0 | G373: 0
A374: 8845 | B374: Jacob Kohn | C374: Austrian, 1791–1868 | D374: Austrian | E374: male | F374: 1791 | G374: 1868
A375: 9325 | B375: Japan Victor Corporation (JVC), Japan | C375: est. 1927 | F375: 1927 | G375: 0
A376: 9339 | B376: Coors Porcelain Co., Golden, CO | C376: American, est. 1910 | D376: American | F376: 1910 | G376: 0
A377: 9555 | B377: Technics, Osaka, Japan | C377: est. 1965 | D377: Japanese | F377: 1965 | G377: 0
A378: 9682 | B378: Daum Frères, Nancy, France | C378: French, established 1875 | D378: French | F378: 1875 | G378: 0
A379: 9724 | B379: Lalance & Grosjean Mfg. Co., Woodhaven, NY | D379: American | F379: 0 | G379: 0
A380: 9953 | B380: American Steel & Wire Co., Worcester, MA | C380: American, established 1898 | D380: American | F380: 1898 | G380: 0
A381: 9958 | B381: Aluminum Company of America, Pittsburgh, Pennsylvania | C381: est 1888 | D381: American | F381: 1888 | G381: 0
A382: 10027 | B382: The Aluminum Cooking Utensil Co., New York, NY | C382: est. 1901 | D382: American | F382: 1901 | G382: 0
A383: 10113 | B383: S.K.F. Industries, Inc., Hartford, CT | D383: American | F383: 0 | G383: 0
A384: 10121 | B384: Scovill Mfg. Co., Plumbers Brass Goods Div., Waterbury, CT | C384: American, established 1802 | D384: American | F384: 1802 | G384: 0
A385: 10302 | B385: Owens-Illinois Glass Co., Toledo, OH | C385: American, est. 1903 | D385: American | F385: 1903 | G385: 0
A386: 10582 | B386: J. & J. Kohn, Vienna | C386: est. 1867 | F386: 1867 | G386: 0
A387: 10725 | B387: Smart Design, New York | C387: American, est. 1979 | D387: American | F387: 1979 | G387: 0
A388: 11936 | B388: Octavio Paz | C388: Mexican, 1914–1998 | D388: Mexican | E388: male | F388: 1914 | G388: 1998
A389: 11993 | B389: Joyce Mansour | C389: British, 1928–1987 | D389: British | E389: female | F389: 1928 | G389: 1987
A390: 12340 | B390: Michel Leiris | C390: French, 1901–1990 | D390: French | E390: male | F390: 1901 | G390: 1990
A391: 12582 | B391: Robert Cordier | C391: Belgian, 1933 – 2020 | D391: Belgian | E391: male | F391: 1933 | G391: 2020
A392: 12594 | B392: Paul Bowles | C392: American and Moroccan, 1910 – 1999 | E392: male | F392: 1910 | G392: 1999
A393: 13407 | B393: Gregory Corso | C393: American, 1930 – 2001 | D393: American | E393: male | F393: 1930 | G393: 2001
A394: 13574 | B394: William S. Burroughs | C394: American, 1914–1997 | D394: American | E394: male | F394: 1914 | G394: 1997
A395: 13599 | B395: Edouard Jaguer | C395: French, 1924 – 2006 | D395: French | E395: male | F395: 1924 | G395: 2006
A396: 13634 | B396: Robert Lebel | C396: French, 1901 – 1986 | D396: French | E396: male | F396: 1901 | G396: 1986
A397: 14164 | B397: Michael McClure | C397: American, 1932 – 2020 | D397: American | E397: male | F397: 1932 | G397: 2020
A398: 14558 | B398: Anne Waldman | C398: American, born 1945 | D398: American | E398: female | F398: 1945 | G398: 0
...

Sheet Artworks
A1: ObjectID | B1: Title | C1: ConstituentID | D1: Artists | E1: Date | F1: Clean Date | G1: Medium | H1: Dimensions | I1: Classification | J1: Department | K1: DateAcquired | L1: URL | M1: ImageURL | N1: OnView
A2: 257 | B2: Simulated Dwelling for a Family of Five Project | C2: 2864 | D2: {=_xlfn.TEXTJOIN(",",TRUE,_xlfn.XLOOKUP(_xlfn.TEXTSPLIT(C2,",")*1,_xlfn._TRO_TRAILING(Artists!A:A),_xlfn._TRO_TRAILING(Artists!B:B)))} -> David Jacob | E2: 1970 | F2: {=_xlfn.REGEXEXTRACT(E2,"\d{4}")*1} -> 1970 | G2: Fiberglass, polyester resin, metal, paper, plastic and synthetic polymer paint | H2: 28 x 34 3/8 x 34 3/8" (71.1 x 87.3 x 87.3 cm) | I2: Architecture | J2: Architecture & Design | K2: 26792 | L2: https://www.moma.org/collection/works/257 | M2: https://www.moma.org/media/W1siZiIsIjIyODY1OCJdLFsicCIsImNvbnZlcnQiLCItcmVzaXplIDEwMjR4MTAyNFx1MDAzZSJdXQ.jpg?sha=0f4261daac246e9b | N2: Floor 4, 417
A3: 775 | B3: Concrete Office Building Project, Berlin, Germany (Exterior perspective) | C3: 7166 | D3: {=_xlfn.TEXTJOIN(",",TRUE,_xlfn.XLOOKUP(_xlfn.TEXTSPLIT(C3,",")*1,_xlfn._TRO_TRAILING(Artists!A:A),_xlfn._TRO_TRAILING(Artists!B:B)))} -> Ludwig Mies van der Rohe | E3: 1923 | F3: {=_xlfn.REGEXEXTRACT(E3,"\d{4}")*1} -> 1923 | G3: Charcoal and crayon on paper | H3: 54 1/2 x 113 3/4" (138.4 x 288.9 cm) | I3: Mies van der Rohe Archive | J3: Architecture & Design | K3: 24904 | L3: https://www.moma.org/collection/works/775 | M3: https://www.moma.org/media/W1siZiIsIjQwMDE2MSJdLFsicCIsImNvbnZlcnQiLCItcmVzaXplIDEwMjR4MTAyNFx1MDAzZSJdXQ.jpg?sha=110180447018c67d | N3: Floor 5, 511
A4: 941 | B4: Furniture Manufacturers Association Headquarters, project, High Wycombe, England, Side elevation | C4: 7987 | D4: {=_xlfn.TEXTJOIN(",",TRUE,_xlfn.XLOOKUP(_xlfn.TEXTSPLIT(C4,",")*1,_xlfn._TRO_TRAILING(Artists!A:A),_xlfn._TRO_TRAILING(Artists!B:B)))} -> Michael Webb | E4: 1957-58 | F4: {=_xlfn.REGEXEXTRACT(E4,"\d{4}")*1} -> 1957 | G4: Graphite and ink on tracing paper mounted on board | H4: 23 1/2 x 32" (59.7 x 81.3 cm) | I4: Architecture | J4: Architecture & Design | K4: 36111 | L4: https://www.moma.org/collection/works/941 | M4: https://www.moma.org/media/W1siZiIsIjUzMDIyMSJdLFsicCIsImNvbnZlcnQiLCItcmVzaXplIDEwMjR4MTAyNFx1MDAzZSJdXQ.jpg?sha=2964904217fe93e6 | N4: Floor 4, 417
A5: 1007 | B5: Column Cover for the German Pavilion, International Exposition, Barcelona, Spain | C5: 7166 | D5: {=_xlfn.TEXTJOIN(",",TRUE,_xlfn.XLOOKUP(_xlfn.TEXTSPLIT(C5,",")*1,_xlfn._TRO_TRAILING(Artists!A:A),_xlfn._TRO_TRAILING(Artists!B:B)))} -> Ludwig Mies van der Rohe | E5: 1928-29 | F5: {=_xlfn.REGEXEXTRACT(E5,"\d{4}")*1} -> 1928 | G5: Chrome-plated steel | H5: 118 1/2 x 6 1/2 x 6 1/2" (301 x 16.5 x 16.5 cm) | I5: Architecture | J5: Architecture & Design | K5: 31692 | L5: https://www.moma.org/collection/works/1007 | M5: https://www.moma.org/media/W1siZiIsIjIxMDkyNSJdLFsicCIsImNvbnZlcnQiLCItcmVzaXplIDEwMjR4MTAyNFx1MDAzZSJdXQ.jpg?sha=f09f4ba416d3a81e | N5: Floor 5, 511
A6: 1512 | B6: Carna Folding Wheelchair | C6: 7440 | D6: {=_xlfn.TEXTJOIN(",",TRUE,_xlfn.XLOOKUP(_xlfn.TEXTSPLIT(C6,",")*1,_xlfn._TRO_TRAILING(Artists!A:A),_xlfn._TRO_TRAILING(Artists!B:B)))} -> Kazuo Kawasaki | E6: 1989 | F6: {=_xlfn.REGEXEXTRACT(E6,"\d{4}")*1} -> 1989 | G6: Titanium, rubber, and aluminum honeycomb | H6: 33 x 22 x 35 1/4" (83.8 x 55.9 x 89.5 cm) | I6: Design | J6: Architecture & Design | K6: 34716 | L6: https://www.moma.org/collection/works/1512 | M6: https://www.moma.org/media/W1siZiIsIjIxMDAyMSJdLFsicCIsImNvbnZlcnQiLCItcmVzaXplIDEwMjR4MTAyNFx1MDAzZSJdXQ.jpg?sha=3b7076d407aab09b | N6: Floor 4, 417
A7: 1621 | B7: Mind Expander / Flyhead Helmet | C7: 8412, 8413, 7561, 8414, 7562 | D7: {=_xlfn.TEXTJOIN(",",TRUE,_xlfn.XLOOKUP(_xlfn.TEXTSPLIT(C7,",")*1,_xlfn._TRO_TRAILING(Artists!A:A),_xlfn._TRO_TRAILING(Artists!B:B)))} -> Haus-Rucker-Co,Günter Zamp Kelp,Laurids Ortner,Klaus Pinter,Manfred Ortner | E7: 1968 | F7: {=_xlfn.REGEXEXTRACT(E7,"\d{4}")*1} -> 1968 | M7: https://www.moma.org/media/W1siZiIsIjQyMDk5MSJdLFsicCIsImNvbnZlcnQiLCItcmVzaXplIDEwMjR4MTAyNFx1MDAzZSJdXQ.jpg?sha=e47c3b5df9258394 | N7: Floor 4, 417
A8: 1825 | B8: Juicy Salif Lemon Squeezer | C8: 8418 | D8: {=_xlfn.TEXTJOIN(",",TRUE,_xlfn.XLOOKUP(_xlfn.TEXTSPLIT(C8,",")*1,_xlfn._TRO_TRAILING(Artists!A:A),_xlfn._TRO_TRAILING(Artists!B:B)))} -> Philippe Starck | E8: 1988 | F8: {=_xlfn.REGEXEXTRACT(E8,"\d{4}")*1} -> 1988 | G8: P.T.F.E.-treated pressure cast aluminum and polyamide | H8: 11 1/2 x 5" (29.2 x 12.7 cm) | I8: Design | J8: Architecture & Design | K8: 36544 | L8: https://www.moma.org/collection/works/1825 | M8: https://www.moma.org/media/W1siZiIsIjIxMDExNyJdLFsicCIsImNvbnZlcnQiLCItcmVzaXplIDEwMjR4MTAyNFx1MDAzZSJdXQ.jpg?sha=1b9d4471735839d3 | N8: Floor 1, 1 South
A9: 1911 | B9: Max-2 Stacking Cups | C9: 6155 | D9: {=_xlfn.TEXTJOIN(",",TRUE,_xlfn.XLOOKUP(_xlfn.TEXTSPLIT(C9,",")*1,_xlfn._TRO_TRAILING(Artists!A:A),_xlfn._TRO_TRAILING(Artists!B:B)))} -> Massimo Vignelli | E9: 1970 | F9: {=_xlfn.REGEXEXTRACT(E9,"\d{4}")*1} -> 1970 | G9: Plastic | H9: Each: 2 3/4 x 6 1/4 x 7 1/2" (7 x 15.9 x 19.1 cm) | I9: Design | J9: Architecture & Design | K9: 26400 | L9: https://www.moma.org/collection/works/1911 | M9: https://www.moma.org/media/W1siZiIsIjIxMDE0OSJdLFsicCIsImNvbnZlcnQiLCItcmVzaXplIDEwMjR4MTAyNFx1MDAzZSJdXQ.jpg?sha=bd4f4bc76f2d531e | N9: Floor 1, 1 South
A10: 1964 | B10: Tilt-Back Side Chair | C10: 1671, 1672 | D10: {=_xlfn.TEXTJOIN(",",TRUE,_xlfn.XLOOKUP(_xlfn.TEXTSPLIT(C10,",")*1,_xlfn._TRO_TRAILING(Artists!A:A),_xlfn._TRO_TRAILING(Artists!B:B)))} -> Charles Eames,Ray Eames | E10: c. 1944 | F10: {=_xlfn.REGEXEXTRACT(E10,"\d{4}")*1} -> 1944 | G10: Molded plywood, metal rod, rubber shockmounts, and rubber glides | H10: 25 3/4 x 20 x 29" (65.4 x 50.8 x 73.7 cm) | I10: Design | J10: Architecture & Design | K10: 16929 | L10: https://www.moma.org/collection/works/1964 | M10: https://www.moma.org/media/W1siZiIsIjIyNjM3MyJdLFsicCIsImNvbnZlcnQiLCItcmVzaXplIDEwMjR4MTAyNFx1MDAzZSJdXQ.jpg?sha=16733e2d84824824 | N10: Floor 1, 1 South
A11: 2067 | B11: Little River | C11: 5814 | D11: {=_xlfn.TEXTJOIN(",",TRUE,_xlfn.XLOOKUP(_xlfn.TEXTSPLIT(C11,",")*1,_xlfn._TRO_TRAILING(Artists!A:A),_xlfn._TRO_TRAILING(Artists!B:B)))} -> Lenore Tawney | E11: 1968 | F11: {=_xlfn.REGEXEXTRACT(E11,"\d{4}")*1} -> 1968 | G11: Linen | H11: 91 1/2 x 21" (232.4 x 53.3 cm) | I11: Design | J11: Architecture & Design | L11: https://www.moma.org/collection/works/2067 | M11: https://www.moma.org/media/W1siZiIsIjM5MTE5NSJdLFsicCIsImNvbnZlcnQiLCItcmVzaXplIDEwMjR4MTAyNFx1MDAzZSJdXQ.jpg?sha=19d84324c8dea7de | N11: Floor 5, 516
A12: 2133 | B12: Prototype for Chaise Longue (La Chaise) | C12: 1671, 1672 | D12: {=_xlfn.TEXTJOIN(",",TRUE,_xlfn.XLOOKUP(_xlfn.TEXTSPLIT(C12,",")*1,_xlfn._TRO_TRAILING(Artists!A:A),_xlfn._TRO_TRAILING(Artists!B:B)))} -> Charles Eames,Ray Eames | E12: 1948 | F12: {=_xlfn.REGEXEXTRACT(E12,"\d{4}")*1} -> 1948 | G12: Hard rubber foam, plastic, wood, and metal | H12: 32 1/2 x 59 x 34 1/4" (82.5 x 149.8 x 87 cm) | I12: Design | J12: Architecture & Design | K12: 26792 | L12: https://www.moma.org/collection/works/2133 | M12: https://www.moma.org/media/W1siZiIsIjIxMjEwNCJdLFsicCIsImNvbnZlcnQiLCItcmVzaXplIDEwMjR4MTAyNFx1MDAzZSJdXQ.jpg?sha=a829eced7842c23c | N12: Floor 1, 1 South
A13: 2200 | B13: Pitcher | C13: 1968 | D13: {=_xlfn.TEXTJOIN(",",TRUE,_xlfn.XLOOKUP(_xlfn.TEXTSPLIT(C13,",")*1,_xlfn._TRO_TRAILING(Artists!A:A),_xlfn._TRO_TRAILING(Artists!B:B)))} -> Kaj Franck | E13: 1954 | F13: {=_xlfn.REGEXEXTRACT(E13,"\d{4}")*1} -> 1954 | G13: Turn mold-blown glass | H13: h. 8 3/4" (22.2 cm), diam. 3 7/8" (9.9 cm) | I13: Design | J13: Architecture & Design | K13: 33618 | L13: https://www.moma.org/collection/works/2200 | M13: https://www.moma.org/media/W1siZiIsIjIyODAxMiJdLFsicCIsImNvbnZlcnQiLCItcmVzaXplIDEwMjR4MTAyNFx1MDAzZSJdXQ.jpg?sha=14397e948a30d891 | N13: Floor 1, 1 South
A14: 2205 | B14: Tumblers | C14: 1968 | D14: {=_xlfn.TEXTJOIN(",",TRUE,_xlfn.XLOOKUP(_xlfn.TEXTSPLIT(C14,",")*1,_xlfn._TRO_TRAILING(Artists!A:A),_xlfn._TRO_TRAILING(Artists!B:B)))} -> Kaj Franck | E14: 1954 | F14: {=_xlfn.REGEXEXTRACT(E14,"\d{4}")*1} -> 1954 | G14: Turn mold-blown glass | H14: Each: 3 1/4 x 3 1/8" (8.3 x 8 cm) | I14: Design | J14: Architecture & Design | K14: 33618 | L14: https://www.moma.org/collection/works/2205 | M14: https://www.moma.org/media/W1siZiIsIjIyODAxMyJdLFsicCIsImNvbnZlcnQiLCItcmVzaXplIDEwMjR4MTAyNFx1MDAzZSJdXQ.jpg?sha=6e69bbb923df7620 | N14: Floor 1, 1 South
A15: 2234 | B15: Bell-47D1 Helicopter | C15: 6518 | D15: {=_xlfn.TEXTJOIN(",",TRUE,_xlfn.XLOOKUP(_xlfn.TEXTSPLIT(C15,",")*1,_xlfn._TRO_TRAILING(Artists!A:A),_xlfn._TRO_TRAILING(Artists!B:B)))} -> Arthur Young | E15: 1945 | F15: {=_xlfn.REGEXEXTRACT(E15,"\d{4}")*1} -> 1945 | G15: Aluminum, steel, and acrylic plastic | H15: 9' 2 3/4" x 7' 11" x 42' 8 3/4" (281.3 x 302 x 1271.9 cm) | I15: Design | J15: Architecture & Design | K15: 30985 | L15: https://www.moma.org/collection/works/2234 | M15: https://www.moma.org/media/W1siZiIsIjI0ODkwMCJdLFsicCIsImNvbnZlcnQiLCItcmVzaXplIDEwMjR4MTAyNFx1MDAzZSJdXQ.jpg?sha=1e29acec814a8870 | N15: Floor 3
A16: 2267 | B16: Dark River | C16: 5814 | D16: {=_xlfn.TEXTJOIN(",",TRUE,_xlfn.XLOOKUP(_xlfn.TEXTSPLIT(C16,",")*1,_xlfn._TRO_TRAILING(Artists!A:A),_xlfn._TRO_TRAILING(Artists!B:B)))} -> Lenore Tawney | E16: 1962 | F16: {=_xlfn.REGEXEXTRACT(E16,"\d{4}")*1} -> 1962 | G16: Linen and wood | H16: 164 x 22 1/2" (416.6 x 57.2 cm) | I16: Design | J16: Architecture & Design | K16: 23055 | L16: https://www.moma.org/collection/works/2267 | M16: https://www.moma.org/media/W1siZiIsIjI4NDc1MCJdLFsicCIsImNvbnZlcnQiLCItcmVzaXplIDEwMjR4MTAyNFx1MDAzZSJdXQ.jpg?sha=e0591a2e13829cbe | N16: Floor 1
A17: 2294 | B17: Side Chair (model DCMU) | C17: 1671, 1672 | D17: {=_xlfn.TEXTJOIN(",",TRUE,_xlfn.XLOOKUP(_xlfn.TEXTSPLIT(C17,",")*1,_xlfn._TRO_TRAILING(Artists!A:A),_xlfn._TRO_TRAILING(Artists!B:B)))} -> Charles Eames,Ray Eames | E17: 1969 | F17: {=_xlfn.REGEXEXTRACT(E17,"\d{4}")*1} -> 1969 | G17: Polyester reinforced with glass fibers, steel tube, Naugahyde with polyurethane foam padding, vinyl, and nylon | H17: Each: 29 1/2 x 19 1/2 x 21 1/2" (74.9 x 49.5 x 54.6 cm) | I17: Design | J17: Architecture & Design | K17: 26792 | L17: https://www.moma.org/collection/works/2294 | M17: https://www.moma.org/media/W1siZiIsIjIyODQzNCJdLFsicCIsImNvbnZlcnQiLCItcmVzaXplIDEwMjR4MTAyNFx1MDAzZSJdXQ.jpg?sha=e89eae257b2fbd95 | N17: Floor 1, 1 South
A18: 2334 | B18: Child's cradle (model 1573) | C18: 8182, 8845, 10582 | D18: {=_xlfn.TEXTJOIN(",",TRUE,_xlfn.XLOOKUP(_xlfn.TEXTSPLIT(C18,",")*1,_xlfn._TRO_TRAILING(Artists!A:A),_xlfn._TRO_TRAILING(Artists!B:B)))} -> Josef Kohn,Jacob Kohn,J. & J. Kohn, Vienna | E18: c. 1895 | F18: {=_xlfn.REGEXEXTRACT(E18,"\d{4}")*1} -> 1895 | G18: Ebonized bent beechwood | H18: 80 1/4 x 56 1/4 x 25 7/16" (203.8 x 142.9 x 64.6 cm) | I18: Design | J18: Architecture & Design | K18: 34093 | L18: https://www.moma.org/collection/works/2334 | M18: https://www.moma.org/media/W1siZiIsIjIxMDUyNSJdLFsicCIsImNvbnZlcnQiLCItcmVzaXplIDEwMjR4MTAyNFx1MDAzZSJdXQ.jpg?sha=b953728b4dac2621 | N18: Floor 5, 504
A19: 2363 | B19: Vase | C19: 9682 | D19: {=_xlfn.TEXTJOIN(",",TRUE,_xlfn.XLOOKUP(_xlfn.TEXTSPLIT(C19,",")*1,_xlfn._TRO_TRAILING(Artists!A:A),_xlfn._TRO_TRAILING(Artists!B:B)))} -> Daum Frères, Nancy, France | E19: c. 1900 | F19: {=_xlfn.REGEXEXTRACT(E19,"\d{4}")*1} -> 1900 | G19: Hand-painted sculptured glass | H19: 21 1/2 × 4 3/8 × 4 1/4" (54.6 × 11.1 × 10.8 cm) | I19: Design | J19: Architecture & Design | K19: 21523 | L19: https://www.moma.org/collection/works/2363 | M19: https://www.moma.org/media/W1siZiIsIjU1NjIwMyJdLFsicCIsImNvbnZlcnQiLCItcmVzaXplIDEwMjR4MTAyNFx1MDAzZSJdXQ.jpg?sha=7a3c71ef95e440e1 | N19: Floor 5, 501
A20: 2368 | B20: Le Parthènon Vase | C20: 9682 | D20: {=_xlfn.TEXTJOIN(",",TRUE,_xlfn.XLOOKUP(_xlfn.TEXTSPLIT(C20,",")*1,_xlfn._TRO_TRAILING(Artists!A:A),_xlfn._TRO_TRAILING(Artists!B:B)))} -> Daum Frères, Nancy, France | E20: c. 1900 | F20: {=_xlfn.REGEXEXTRACT(E20,"\d{4}")*1} -> 1900 | G20: Painted glass | H20: 15 3/16 × 3 1/4 × 3 1/2" (38.6 × 8.3 × 8.9 cm) | I20: Design | J20: Architecture & Design | K20: 21523 | L20: https://www.moma.org/collection/works/2368 | M20: https://www.moma.org/media/W1siZiIsIjIyODUxMiJdLFsicCIsImNvbnZlcnQiLCItcmVzaXplIDEwMjR4MTAyNFx1MDAzZSJdXQ.jpg?sha=558a588d4e27c5cd | N20: Floor 5, 501
A21: 2373 | B21: Vase | C21: 9682 | D21: {=_xlfn.TEXTJOIN(",",TRUE,_xlfn.XLOOKUP(_xlfn.TEXTSPLIT(C21,",")*1,_xlfn._TRO_TRAILING(Artists!A:A),_xlfn._TRO_TRAILING(Artists!B:B)))} -> Daum Frères, Nancy, France | E21: c. 1900 | F21: {=_xlfn.REGEXEXTRACT(E21,"\d{4}")*1} -> 1900 | G21: Painted glass | H21: 18 1/8 × 3 1/4 × 2 1/2" (46 × 8.3 × 6.4 cm) | I21: Design | J21: Architecture & Design | K21: 21523 | L21: https://www.moma.org/collection/works/2373 | M21: https://www.moma.org/media/W1siZiIsIjIyODUxOSJdLFsicCIsImNvbnZlcnQiLCItcmVzaXplIDEwMjR4MTAyNFx1MDAzZSJdXQ.jpg?sha=e351bfe7021e1a18 | N21: Floor 5, 501
A22: 2377 | B22: Vase | C22: 9682 | D22: {=_xlfn.TEXTJOIN(",",TRUE,_xlfn.XLOOKUP(_xlfn.TEXTSPLIT(C22,",")*1,_xlfn._TRO_TRAILING(Artists!A:A),_xlfn._TRO_TRAILING(Artists!B:B)))} -> Daum Frères, Nancy, France | E22: c. 1900 | F22: {=_xlfn.REGEXEXTRACT(E22,"\d{4}")*1} -> 1900 | G22: Painted glass | H22: 8 1/4 x 3 1/2 x 2 3/4" (21 x 8.9 x 7 cm) | I22: Design | J22: Architecture & Design | K22: 21523 | L22: https://www.moma.org/collection/works/2377 | M22: https://www.moma.org/media/W1siZiIsIjIxMDU1NiJdLFsicCIsImNvbnZlcnQiLCItcmVzaXplIDEwMjR4MTAyNFx1MDAzZSJdXQ.jpg?sha=8fe2792e391d8c24 | N22: Floor 5, 501
A23: 2381 | B23: Miniature Vase | C23: 9682 | D23: {=_xlfn.TEXTJOIN(",",TRUE,_xlfn.XLOOKUP(_xlfn.TEXTSPLIT(C23,",")*1,_xlfn._TRO_TRAILING(Artists!A:A),_xlfn._TRO_TRAILING(Artists!B:B)))} -> Daum Frères, Nancy, France | E23: c. 1900 | F23: {=_xlfn.REGEXEXTRACT(E23,"\d{4}")*1} -> 1900 | G23: Painted glass | H23: 5 7/8 × 1 7/8 × 1 7/8" (14.9 × 4.8 × 4.8 cm) | I23: Design | J23: Architecture & Design | K23: 21523 | L23: https://www.moma.org/collection/works/2381 | M23: https://www.moma.org/media/W1siZiIsIjIyODUyMyJdLFsicCIsImNvbnZlcnQiLCItcmVzaXplIDEwMjR4MTAyNFx1MDAzZSJdXQ.jpg?sha=4000408274c1db9c | N23: Floor 5, 501
A24: 2384 | B24: Miniature Vase | C24: 9682 | D24: {=_xlfn.TEXTJOIN(",",TRUE,_xlfn.XLOOKUP(_xlfn.TEXTSPLIT(C24,",")*1,_xlfn._TRO_TRAILING(Artists!A:A),_xlfn._TRO_TRAILING(Artists!B:B)))} -> Daum Frères, Nancy, France | E24: c. 1900 | F24: {=_xlfn.REGEXEXTRACT(E24,"\d{4}")*1} -> 1900 | G24: Hand-painted sculptured glass | H24: 6 × 2 × 2" (15.2 × 5.1 × 5.1 cm) | I24: Design | J24: Architecture & Design | K24: 21523 | L24: https://www.moma.org/collection/works/2384 | M24: https://www.moma.org/media/W1siZiIsIjIyODU5NyJdLFsicCIsImNvbnZlcnQiLCItcmVzaXplIDEwMjR4MTAyNFx1MDAzZSJdXQ.jpg?sha=57006abd13064ad0 | N24: Floor 5, 501
A25: 2393 | B25: Entrance Gate to Paris Subway (Métropolitain) Station, Paris, France | C25: 2407 | D25: {=_xlfn.TEXTJOIN(",",TRUE,_xlfn.XLOOKUP(_xlfn.TEXTSPLIT(C25,",")*1,_xlfn._TRO_TRAILING(Artists!A:A),_xlfn._TRO_TRAILING(Artists!B:B)))} -> Hector Guimard | E25: c. 1900 | F25: {=_xlfn.REGEXEXTRACT(E25,"\d{4}")*1} -> 1900 | G25: Painted cast iron, glazed lava, and glass | H25: 13' 11" x 17' 10" x 32" (424.2 x 543.6 x 81.3 cm)_x000D_ Each vertical stanchion: 1040 lbs. Horizontal component: 460 lbs. Glazed lava sign: 100 lbs. | I25: Architecture | J25: Architecture & Design | K25: 21523 | L25: https://www.moma.org/collection/works/2393 | M25: https://www.moma.org/media/W1siZiIsIjI0MDYzNCJdLFsicCIsImNvbnZlcnQiLCItcmVzaXplIDEwMjR4MTAyNFx1MDAzZSJdXQ.jpg?sha=9ec928b17dd8619b | N25: Floor 1, Sculpture Garden
A26: 2565 | B26: Tulip Armchair (model 150) | C26: 5103 | D26: {=_xlfn.TEXTJOIN(",",TRUE,_xlfn.XLOOKUP(_xlfn.TEXTSPLIT(C26,",")*1,_xlfn._TRO_TRAILING(Artists!A:A),_xlfn._TRO_TRAILING(Artists!B:B)))} -> Eero Saarinen | E26: 1955-56 | F26: {=_xlfn.REGEXEXTRACT(E26,"\d{4}")*1} -> 1955 | G26: Fiberglass-reinforced polyester and cast aluminum | H26: 31 1/2 x 25 1/4 x 23 1/2" (80 x 64.1 x 59.7 cm) | I26: Design | J26: Architecture & Design | K26: 21523 | L26: https://www.moma.org/collection/works/2565 | M26: https://www.moma.org/media/W1siZiIsIjUxNzkwNCJdLFsicCIsImNvbnZlcnQiLCItcmVzaXplIDEwMjR4MTAyNFx1MDAzZSJdXQ.jpg?sha=c735b3f62bac1931 | N26: Floor 1, 1 South
A27: 2659 | B27: Bearing Spring | C27: 9953 | D27: {=_xlfn.TEXTJOIN(",",TRUE,_xlfn.XLOOKUP(_xlfn.TEXTSPLIT(C27,",")*1,_xlfn._TRO_TRAILING(Artists!A:A),_xlfn._TRO_TRAILING(Artists!B:B)))} -> American Steel & Wire Co., Worcester, MA | E27: Before 1934 | F27: {=_xlfn.REGEXEXTRACT(E27,"\d{4}")*1} -> 1934 | G27: Steel | H27: 2 1/2 x 1 5/16" (6.4 x 3.4 cm) | I27: Design | J27: Architecture & Design | K27: 12510 | L27: https://www.moma.org/collection/works/2659 | M27: https://www.moma.org/media/W1siZiIsIjIxMDY4NyJdLFsicCIsImNvbnZlcnQiLCItcmVzaXplIDEwMjR4MTAyNFx1MDAzZSJdXQ.jpg?sha=f6c14e8dd33a4ac4 | N27: Floor 5, 511
A28: 2682 | B28: Self-Aligning Ball Bearing | C28: 6394 | D28: {=_xlfn.TEXTJOIN(",",TRUE,_xlfn.XLOOKUP(_xlfn.TEXTSPLIT(C28,",")*1,_xlfn._TRO_TRAILING(Artists!A:A),_xlfn._TRO_TRAILING(Artists!B:B)))} -> Sven Wingquist | E28: 1907 | F28: {=_xlfn.REGEXEXTRACT(E28,"\d{4}")*1} -> 1907 | G28: Chrome-plated steel | H28: 1 3/4 x 8 1/2" (4.4 x 21.6 cm) | I28: Design | J28: Architecture & Design | K28: 12510 | L28: https://www.moma.org/collection/works/2682 | M28: https://www.moma.org/media/W1siZiIsIjIxMDcwMCJdLFsicCIsImNvbnZlcnQiLCItcmVzaXplIDEwMjR4MTAyNFx1MDAzZSJdXQ.jpg?sha=805516127e63e161 | N28: Floor 5, 511
A29: 2704 | B29: Flush Valve | C29: 10121 | D29: {=_xlfn.TEXTJOIN(",",TRUE,_xlfn.XLOOKUP(_xlfn.TEXTSPLIT(C29,",")*1,_xlfn._TRO_TRAILING(Artists!A:A),_xlfn._TRO_TRAILING(Artists!B:B)))} -> Scovill Mfg. Co., Plumbers Brass Goods Div., Waterbury, CT | E29: Before 1934 | F29: {=_xlfn.REGEXEXTRACT(E29,"\d{4}")*1} -> 1934 | G29: Chromium | H29: 13 3/8 × 12 × 3 3/4" (34 × 30.5 × 9.5 cm) | I29: Design | J29: Architecture & Design | K29: 12420 | L29: https://www.moma.org/collection/works/2704 | M29: https://www.moma.org/media/W1siZiIsIjIxMDcxMiJdLFsicCIsImNvbnZlcnQiLCItcmVzaXplIDEwMjR4MTAyNFx1MDAzZSJdXQ.jpg?sha=b1f0b041fbdb5455 | N29: Floor 5, 511
A30: 2728 | B30: Akari Floor Lamp (model 2P) | C30: 4324 | D30: {=_xlfn.TEXTJOIN(",",TRUE,_xlfn.XLOOKUP(_xlfn.TEXTSPLIT(C30,",")*1,_xlfn._TRO_TRAILING(Artists!A:A),_xlfn._TRO_TRAILING(Artists!B:B)))} -> Isamu Noguchi | E30: c. 1968 | F30: {=_xlfn.REGEXEXTRACT(E30,"\d{4}")*1} -> 1968 | G30: Paper shade and metal frame | H30: h. 30" (76.2 cm) | I30: Design | J30: Architecture & Design | K30: 28548 | L30: https://www.moma.org/collection/works/2728 | M30: https://www.moma.org/media/W1siZiIsIjIyODgwOSJdLFsicCIsImNvbnZlcnQiLCItcmVzaXplIDEwMjR4MTAyNFx1MDAzZSJdXQ.jpg?sha=cf7fba4d2ac5f3b6 | N30: Floor 1, 1 South
A31: 2731 | B31: Steel Balls | C31: 10113 | D31: {=_xlfn.TEXTJOIN(",",TRUE,_xlfn.XLOOKUP(_xlfn.TEXTSPLIT(C31,",")*1,_xlfn._TRO_TRAILING(Artists!A:A),_xlfn._TRO_TRAILING(Artists!B:B)))} -> S.K.F. Industries, Inc., Hartford, CT | E31: Before 1934 | F31: {=_xlfn.REGEXEXTRACT(E31,"\d{4}")*1} -> 1934 | G31: Nickel-plated steel | H31: Dimensions range from a minimum diameter of 3/8" (1 cm) to a max diameter of 1" (2.5 cm) | I31: Design | J31: Architecture & Design | K31: 12510 | L31: https://www.moma.org/collection/works/2731 | M31: https://www.moma.org/media/W1siZiIsIjIxMDcyOSJdLFsicCIsImNvbnZlcnQiLCItcmVzaXplIDEwMjR4MTAyNFx1MDAzZSJdXQ.jpg?sha=80b58dcb7f6b0c95 | N31: Floor 5, 511
A32: 2805 | B32: Boiling Flasks | C32: 1249 | D32: {=_xlfn.TEXTJOIN(",",TRUE,_xlfn.XLOOKUP(_xlfn.TEXTSPLIT(C32,",")*1,_xlfn._TRO_TRAILING(Artists!A:A),_xlfn._TRO_TRAILING(Artists!B:B)))} -> Corning Glass Works, Corning, NY | E32: 1920s | F32: {=_xlfn.REGEXEXTRACT(E32,"\d{4}")*1} -> 1920 | G32: Borosilicate glass | H32: .1: 14 5/8 x 9 1/2" (37.2 x 24.1 cm)_x000D_ .2: 7 x 4" (17.8 x 10.2 cm)_x000D_ .4: 8 1/2 x 5 1/8" (21.6 x 13 cm)_x000D_ .5-.6: 5 5/8 x 3 1/4" (14.3 x 8.2 cm) | I32: Design | J32: Architecture & Design | K32: 12510 | L32: https://www.moma.org/collection/works/2805 | M32: https://www.moma.org/media/W1siZiIsIjIxMDc2MCJdLFsicCIsImNvbnZlcnQiLCItcmVzaXplIDEwMjR4MTAyNFx1MDAzZSJdXQ.jpg?sha=a19a047dbf5a1b7a | N32: Floor 5, 511
A33: 2807 | B33: Chess Set | C33: 3716 | D33: {=_xlfn.TEXTJOIN(",",TRUE,_xlfn.XLOOKUP(_xlfn.TEXTSPLIT(C33,",")*1,_xlfn._TRO_TRAILING(Artists!A:A),_xlfn._TRO_TRAILING(Artists!B:B)))} -> Man Ray (Emmanuel Radnitzky) | E33: 1920–1926 | F33: {=_xlfn.REGEXEXTRACT(E33,"\d{4}")*1} -> 1920 | G33: Silver-plated and oxidized silver-plated brass | H33: Tallest piece: h. 4" (10.2 cm)_x000D_ Case: 2 5/8 x 21 1/4 x 16 1/2" (6.7 x 54 x 41.9 cm) | I33: Design | J33: Architecture & Design | K33: 18422 | L33: https://www.moma.org/collection/works/2807 | M33: https://www.moma.org/media/W1siZiIsIjI1Mjc1OSJdLFsicCIsImNvbnZlcnQiLCItcmVzaXplIDEwMjR4MTAyNFx1MDAzZSJdXQ.jpg?sha=9d8ac151caf39fee | N33: Floor 5, 513
A34: 2816 | B34: Beakers | C34: 9339 | D34: {=_xlfn.TEXTJOIN(",",TRUE,_xlfn.XLOOKUP(_xlfn.TEXTSPLIT(C34,",")*1,_xlfn._TRO_TRAILING(Artists!A:A),_xlfn._TRO_TRAILING(Artists!B:B)))} -> Coors Porcelain Co., Golden, CO | E34: 1920s | F34: {=_xlfn.REGEXEXTRACT(E34,"\d{4}")*1} -> 1920 | G34: Glazed porcelain | H34: .1: 8 3/8 x 5 3/8" (21.2 x 13.7 cm)_x000D_ .3: 6 1/2 x 4 1/4" (16.5 x 10.8 cm)_x000D_ .4: 6 x 3 7/8" (15.2 x 9.8 cm)_x000D_ .5: 5 5/8 x 3 5/8" (14.3 x 9.2 cm)_x000D_ .7: 4 5/8 x 3 1/8" (11.8 x 7.9 cm)_x000D_ .9: 3 3/4 x 2 1/2" (9.5 x 6.4 cm) | I34: Design | J34: Architecture & Design | K34: 12510 | L34: https://www.moma.org/collection/works/2816 | M34: https://www.moma.org/media/W1siZiIsIjIxMDc2MyJdLFsicCIsImNvbnZlcnQiLCItcmVzaXplIDEwMjR4MTAyNFx1MDAzZSJdXQ.jpg?sha=e509fc25b6553176 | N34: Floor 5, 511
A35: 2841 | B35: Spring | C35: 9953 | D35: {=_xlfn.TEXTJOIN(",",TRUE,_xlfn.XLOOKUP(_xlfn.TEXTSPLIT(C35,",")*1,_xlfn._TRO_TRAILING(Artists!A:A),_xlfn._TRO_TRAILING(Artists!B:B)))} -> American Steel & Wire Co., Worcester, MA | E35: Before 1934 | F35: {=_xlfn.REGEXEXTRACT(E35,"\d{4}")*1} -> 1934 | G35: Steel | H35: 2 1/4 x 2 1/4" (5.7 x 5.7 cm) | I35: Design | J35: Architecture & Design | K35: 12510 | L35: https://www.moma.org/collection/works/2841 | M35: https://www.moma.org/media/W1siZiIsIjIxMDc3OCJdLFsicCIsImNvbnZlcnQiLCItcmVzaXplIDEwMjR4MTAyNFx1MDAzZSJdXQ.jpg?sha=4c83ced717ca1447 | N35: Floor 5, 511
A36: 2859 | B36: Hydrometer Jar | C36: 6011 | D36: {=_xlfn.TEXTJOIN(",",TRUE,_xlfn.XLOOKUP(_xlfn.TEXTSPLIT(C36,",")*1,_xlfn._TRO_TRAILING(Artists!A:A),_xlfn._TRO_TRAILING(Artists!B:B)))} -> Unidentified Designer | E36: Before 1934 | F36: {=_xlfn.REGEXEXTRACT(E36,"\d{4}")*1} -> 1934 | G36: Glass | H36: h. 10" (25.4 cm), diam. 11/16" (1.8 cm); base diam. 1 15/16" (4.9 cm) | I36: Design | J36: Architecture & Design | K36: 12510 | L36: https://www.moma.org/collection/works/2859 | M36: https://www.moma.org/media/W1siZiIsIjIxMDc4NyJdLFsicCIsImNvbnZlcnQiLCItcmVzaXplIDEwMjR4MTAyNFx1MDAzZSJdXQ.jpg?sha=8aff4a542a3efc49 | N36: Floor 5, 511
A37: 2890 | B37: Hydrometer Jar | C37: 6011 | D37: {=_xlfn.TEXTJOIN(",",TRUE,_xlfn.XLOOKUP(_xlfn.TEXTSPLIT(C37,",")*1,_xlfn._TRO_TRAILING(Artists!A:A),_xlfn._TRO_TRAILING(Artists!B:B)))} -> Unidentified Designer | E37: Before 1934 | F37: {=_xlfn.REGEXEXTRACT(E37,"\d{4}")*1} -> 1934 | G37: Glass | H37: 6 3/4 x 1 5/8" (17.2 x 4.2 cm) | I37: Design | J37: Architecture & Design | K37: 12510 | L37: https://www.moma.org/collection/works/2890 | M37: https://www.moma.org/media/W1siZiIsIjIxMDgwOSJdLFsicCIsImNvbnZlcnQiLCItcmVzaXplIDEwMjR4MTAyNFx1MDAzZSJdXQ.jpg?sha=9f8bda1f03a4436c | N37: Floor 5, 511
A38: 2891 | B38: Wear-Ever Tea Kettle (model 1403) | C38: 2402 | D38: {=_xlfn.TEXTJOIN(",",TRUE,_xlfn.XLOOKUP(_xlfn.TEXTSPLIT(C38,",")*1,_xlfn._TRO_TRAILING(Artists!A:A),_xlfn._TRO_TRAILING(Artists!B:B)))} -> Lurelle Guild | E38: c. 1932-33 | F38: {=_xlfn.REGEXEXTRACT(E38,"\d{4}")*1} -> 1932 | G38: Aluminum and plastic | H38: 8 1/2 x 9 1/2" (21.6 x 24.1 cm) | I38: Design | J38: Architecture & Design | K38: 16384 | L38: https://www.moma.org/collection/works/2891 | M38: https://www.moma.org/media/W1siZiIsIjIyODkxMSJdLFsicCIsImNvbnZlcnQiLCItcmVzaXplIDEwMjR4MTAyNFx1MDAzZSJdXQ.jpg?sha=13d364be6a47af30 | N38: Floor 5, 511
A39: 2983 | B39: Flores Box | C39: 3766 | D39: {=_xlfn.TEXTJOIN(",",TRUE,_xlfn.XLOOKUP(_xlfn.TEXTSPLIT(C39,",")*1,_xlfn._TRO_TRAILING(Artists!A:A),_xlfn._TRO_TRAILING(Artists!B:B)))} -> Enzo Mari | E39: 1991 | F39: {=_xlfn.REGEXEXTRACT(E39,"\d{4}")*1} -> 1991 | G39: Thermoplastic polymer | H39: 3 x 12 1/4 x 6" (7.6 x 31.1 x 15.2 cm) | I39: Design | J39: Architecture & Design | K39: 35907 | L39: https://www.moma.org/collection/works/2983 | M39: https://www.moma.org/media/W1siZiIsIjIxMDg1MyJdLFsicCIsImNvbnZlcnQiLCItcmVzaXplIDEwMjR4MTAyNFx1MDAzZSJdXQ.jpg?sha=c087e4e6cd38315f | N39: Floor 1, 1 South
A40: 3025 | B40: Bottles | C40: 10302 | D40: {=_xlfn.TEXTJOIN(",",TRUE,_xlfn.XLOOKUP(_xlfn.TEXTSPLIT(C40,",")*1,_xlfn._TRO_TRAILING(Artists!A:A),_xlfn._TRO_TRAILING(Artists!B:B)))} -> Owens-Illinois Glass Co., Toledo, OH | E40: Before 1934 | F40: {=_xlfn.REGEXEXTRACT(E40,"\d{4}")*1} -> 1934 | G40: Glass and plastic | H40: .1: 6 1/2 x 3 1/4" (16.5 x 8.3 cm)_x000D_ .2: 5 1/4 x 2 3/8" (13.4 x 6 cm)_x000D_ .3: 4 1/4 x 2" (10.8 x 5.1 cm) | I40: Design | J40: Architecture & Design | L40: https://www.moma.org/collection/works/3025 | M40: https://www.moma.org/media/W1siZiIsIjIxMDg2OCJdLFsicCIsImNvbnZlcnQiLCItcmVzaXplIDEwMjR4MTAyNFx1MDAzZSJdXQ.jpg?sha=82554ae87c24eaef | N40: Floor 5, 511
A41: 3048 | B41: Compote dish | C41: 4749 | D41: {=_xlfn.TEXTJOIN(",",TRUE,_xlfn.XLOOKUP(_xlfn.TEXTSPLIT(C41,",")*1,_xlfn._TRO_TRAILING(Artists!A:A),_xlfn._TRO_TRAILING(Artists!B:B)))} -> Otto Prutscher | E41: c. 1907 | F41: {=_xlfn.REGEXEXTRACT(E41,"\d{4}")*1} -> 1907 | G41: Flashed and cut glass | H41: 8 x 5 7/8" (20.3 x 15 cm) | I41: Design | J41: Architecture & Design | K41: 31692 | L41: https://www.moma.org/collection/works/3048 | M41: https://www.moma.org/media/W1siZiIsIjIyOTAxNSJdLFsicCIsImNvbnZlcnQiLCItcmVzaXplIDEwMjR4MTAyNFx1MDAzZSJdXQ.jpg?sha=f5f6cbff72ecfe08 | N41: Floor 5, 504
A42: 3072 | B42: Liqueur glasses | C42: 2694 | D42: {=_xlfn.TEXTJOIN(",",TRUE,_xlfn.XLOOKUP(_xlfn.TEXTSPLIT(C42,",")*1,_xlfn._TRO_TRAILING(Artists!A:A),_xlfn._TRO_TRAILING(Artists!B:B)))} -> Josef Hoffmann | E42: c. 1908 | F42: {=_xlfn.REGEXEXTRACT(E42,"\d{4}")*1} -> 1908 | G42: Blown glass | H42: .1: h. 3 1/2" (8.9 cm), diam. 2 3/8" (6 cm)_x000D_ .2: h. 2 3/4" (7 cm), diam. 2 1/2" (6.4 cm)_x000D_ .3: h. 5 1/4" (13.3 cm), diam. 2 1/4" (5.7 cm) | I42: Design | J42: Architecture & Design | K42: 29005 | L42: https://www.moma.org/collection/works/3072 | M42: https://www.moma.org/media/W1siZiIsIjIxMDg5MiJdLFsicCIsImNvbnZlcnQiLCItcmVzaXplIDEwMjR4MTAyNFx1MDAzZSJdXQ.jpg?sha=598b7fc6c6369e9c | N42: Floor 5, 504
A43: 3144 | B43: Crusader Hotel Sauce Pots | C43: 9724 | D43: {=_xlfn.TEXTJOIN(",",TRUE,_xlfn.XLOOKUP(_xlfn.TEXTSPLIT(C43,",")*1,_xlfn._TRO_TRAILING(Artists!A:A),_xlfn._TRO_TRAILING(Artists!B:B)))} -> Lalance & Grosjean Mfg. Co., Woodhaven, NY | E43: 1920s | F43: {=_xlfn.REGEXEXTRACT(E43,"\d{4}")*1} -> 1920 | G43: Stainless steel | H43: .1: 8 x 18 3/4 x 14 1/8" (20.3 x 47.6 x 35.9 cm)_x000D_ .2: 7 x 17 3/8 x 13 1/4" (17.8 x 44.1 x 33.7 cm)_x000D_ .3: 6 x 16 x 11 1/8" (15.2 x 40.6 x 28.3 cm) | I43: Design | J43: Architecture & Design | K43: 12510 | L43: https://www.moma.org/collection/works/3144 | M43: https://www.moma.org/media/W1siZiIsIjIxMDk0MSJdLFsicCIsImNvbnZlcnQiLCItcmVzaXplIDEwMjR4MTAyNFx1MDAzZSJdXQ.jpg?sha=4ba4c3061e6fb3e3 | N43: Floor 5, 511
A44: 3153 | B44: Wear-Ever Hotel Sauté Pans | C44: 10027 | D44: {=_xlfn.TEXTJOIN(",",TRUE,_xlfn.XLOOKUP(_xlfn.TEXTSPLIT(C44,",")*1,_xlfn._TRO_TRAILING(Artists!A:A),_xlfn._TRO_TRAILING(Artists!B:B)))} -> The Aluminum Cooking Utensil Co., New York, NY | E44: Before 1934 | F44: {=_xlfn.REGEXEXTRACT(E44,"\d{4}")*1} -> 1934 | G44: Aluminum | H44: .1: 2 x 6 1/4" (5.1 x 15.9 cm)_x000D_ .2: 2 1/4 x 7 1/4" (5.7 x 18.4 cm)_x000D_ .3: 2 1/2 x 8 1/4" (6.4 x 21 cm)_x000D_ .4: 2 3/4 x 10 1/4" (7 x 26 cm) | I44: Design | J44: Architecture & Design | K44: 12510 | L44: https://www.moma.org/collection/works/3153 | M44: https://www.moma.org/media/W1siZiIsIjIyOTEyMyJdLFsicCIsImNvbnZlcnQiLCItcmVzaXplIDEwMjR4MTAyNFx1MDAzZSJdXQ.jpg?sha=d2860231caa6f1ca | N44: Floor 5, 511
A45: 3169 | B45: Carafe | C45: 5168 | D45: {=_xlfn.TEXTJOIN(",",TRUE,_xlfn.XLOOKUP(_xlfn.TEXTSPLIT(C45,",")*1,_xlfn._TRO_TRAILING(Artists!A:A),_xlfn._TRO_TRAILING(Artists!B:B)))} -> Timo Sarpaneva | E45: 1956 | F45: {=_xlfn.REGEXEXTRACT(E45,"\d{4}")*1} -> 1956 | G45: Glass | H45: 7 5/8 x 3 5/8" (19.4 x 9.2 cm) | I45: Design | J45: Architecture & Design | K45: 21523 | L45: https://www.moma.org/collection/works/3169 | M45: https://www.moma.org/media/W1siZiIsIjIxMDk1NSJdLFsicCIsImNvbnZlcnQiLCItcmVzaXplIDEwMjR4MTAyNFx1MDAzZSJdXQ.jpg?sha=3c7a47bb67011775 | N45: Floor 1, 1 South
A46: 3212 | B46: May Day Lamp | C46: 8149 | D46: {=_xlfn.TEXTJOIN(",",TRUE,_xlfn.XLOOKUP(_xlfn.TEXTSPLIT(C46,",")*1,_xlfn._TRO_TRAILING(Artists!A:A),_xlfn._TRO_TRAILING(Artists!B:B)))} -> Konstantin Grcic | E46: 1998 | F46: {=_xlfn.REGEXEXTRACT(E46,"\d{4}")*1} -> 1998 | G46: Plastic and polycarbonate | H46: 21 x 8 1/2" (53.3 x 21.6 cm) | I46: Design | J46: Architecture & Design | K46: 36341 | L46: https://www.moma.org/collection/works/3212 | M46: https://www.moma.org/media/W1siZiIsIjIxMTAwMyJdLFsicCIsImNvbnZlcnQiLCItcmVzaXplIDEwMjR4MTAyNFx1MDAzZSJdXQ.jpg?sha=41fe5e62d420e0e9 | N46: Floor 1, 1 South
A47: 3250 | B47: Scissors | C47: 271 | D47: {=_xlfn.TEXTJOIN(",",TRUE,_xlfn.XLOOKUP(_xlfn.TEXTSPLIT(C47,",")*1,_xlfn._TRO_TRAILING(Artists!A:A),_xlfn._TRO_TRAILING(Artists!B:B)))} -> Olof Backstrom | E47: Designed 1960-1967, this example 1976 | F47: {=_xlfn.REGEXEXTRACT(E47,"\d{4}")*1} -> 1960 | G47: Plastic and stainless steel | H47: 8 1/2 × 2 3/4 × 1" (21.6 × 7 × 2.5 cm) | I47: Design | J47: Architecture & Design | K47: 28277 | L47: https://www.moma.org/collection/works/3250 | M47: https://www.moma.org/media/W1siZiIsIjIxMTAyNyJdLFsicCIsImNvbnZlcnQiLCItcmVzaXplIDEwMjR4MTAyNFx1MDAzZSJdXQ.jpg?sha=00d9bc3b587dcca1 | N47: Floor 1, 1 South
A48: 3262 | B48: Bud Vase | C48: 9682 | D48: {=_xlfn.TEXTJOIN(",",TRUE,_xlfn.XLOOKUP(_xlfn.TEXTSPLIT(C48,",")*1,_xlfn._TRO_TRAILING(Artists!A:A),_xlfn._TRO_TRAILING(Artists!B:B)))} -> Daum Frères, Nancy, France | E48: c. 1910 | F48: {=_xlfn.REGEXEXTRACT(E48,"\d{4}")*1} -> 1910 | G48: Blown painted glass | H48: 6 × 2 × 2" (15.2 × 5.1 × 5.1 cm) | I48: Design | J48: Architecture & Design | K48: 28277 | L48: https://www.moma.org/collection/works/3262 | M48: https://www.moma.org/media/W1siZiIsIjIyOTI0NCJdLFsicCIsImNvbnZlcnQiLCItcmVzaXplIDEwMjR4MTAyNFx1MDAzZSJdXQ.jpg?sha=5758823a9b12138b | N48: Floor 5, 501
A49: 3266 | B49: Bud Vase | C49: 9682 | D49: {=_xlfn.TEXTJOIN(",",TRUE,_xlfn.XLOOKUP(_xlfn.TEXTSPLIT(C49,",")*1,_xlfn._TRO_TRAILING(Artists!A:A),_xlfn._TRO_TRAILING(Artists!B:B)))} -> Daum Frères, Nancy, France | E49: c. 1910 | F49: {=_xlfn.REGEXEXTRACT(E49,"\d{4}")*1} -> 1910 | G49: Painted glass | H49: 6 3/8 × 2 × 2" (16.2 × 5.1 × 5.1 cm) | I49: Design | J49: Architecture & Design | K49: 28277 | L49: https://www.moma.org/collection/works/3266 | M49: https://www.moma.org/media/W1siZiIsIjIxMTAzNSJdLFsicCIsImNvbnZlcnQiLCItcmVzaXplIDEwMjR4MTAyNFx1MDAzZSJdXQ.jpg?sha=a997c18f32ff43bc | N49: Floor 5, 501
A50: 3269 | B50: Bud Vase | C50: 9682 | D50: {=_xlfn.TEXTJOIN(",",TRUE,_xlfn.XLOOKUP(_xlfn.TEXTSPLIT(C50,",")*1,_xlfn._TRO_TRAILING(Artists!A:A),_xlfn._TRO_TRAILING(Artists!B:B)))} -> Daum Frères, Nancy, France | E50: c. 1910 | F50: {=_xlfn.REGEXEXTRACT(E50,"\d{4}")*1} -> 1910 | G50: Painted glass | H50: 6 1/4 × 2 × 2" (15.9 × 5.1 × 5.1 cm) | I50: Design | J50: Architecture & Design | K50: 28277 | L50: https://www.moma.org/collection/works/3269 | M50: https://www.moma.org/media/W1siZiIsIjIyOTI0OCJdLFsicCIsImNvbnZlcnQiLCItcmVzaXplIDEwMjR4MTAyNFx1MDAzZSJdXQ.jpg?sha=cda7a4c52e6cdcf7 | N50: Floor 5, 501
A51: 3271 | B51: Bud Vase | C51: 9682 | D51: {=_xlfn.TEXTJOIN(",",TRUE,_xlfn.XLOOKUP(_xlfn.TEXTSPLIT(C51,",")*1,_xlfn._TRO_TRAILING(Artists!A:A),_xlfn._TRO_TRAILING(Artists!B:B)))} -> Daum Frères, Nancy, France | E51: c. 1910 | F51: {=_xlfn.REGEXEXTRACT(E51,"\d{4}")*1} -> 1910 | G51: Painted glass | H51: 6 × 2 × 2" (15.2 × 5.1 × 5.1 cm) | I51: Design | J51: Architecture & Design | K51: 28277 | L51: https://www.moma.org/collection/works/3271 | M51: https://www.moma.org/media/W1siZiIsIjIxMTAzOSJdLFsicCIsImNvbnZlcnQiLCItcmVzaXplIDEwMjR4MTAyNFx1MDAzZSJdXQ.jpg?sha=4c7be42c32d0fa12 | N51: Floor 5, 501
A52: 3274 | B52: Bud Vase | C52: 9682 | D52: {=_xlfn.TEXTJOIN(",",TRUE,_xlfn.XLOOKUP(_xlfn.TEXTSPLIT(C52,",")*1,_xlfn._TRO_TRAILING(Artists!A:A),_xlfn._TRO_TRAILING(Artists!B:B)))} -> Daum Frères, Nancy, France | E52: c. 1910 | F52: {=_xlfn.REGEXEXTRACT(E52,"\d{4}")*1} -> 1910 | G52: Blown painted glass | H52: 6 1/4 × 2 × 2" (15.9 × 5.1 × 5.1 cm) | I52: Design | J52: Architecture & Design | K52: 28277 | L52: https://www.moma.org/collection/works/3274 | M52: https://www.moma.org/media/W1siZiIsIjIxMTA0MSJdLFsicCIsImNvbnZlcnQiLCItcmVzaXplIDEwMjR4MTAyNFx1MDAzZSJdXQ.jpg?sha=a728659970e20fef | N52: Floor 5, 501
A53: 3277 | B53: Bud Vase | C53: 9682 | D53: {=_xlfn.TEXTJOIN(",",TRUE,_xlfn.XLOOKUP(_xlfn.TEXTSPLIT(C53,",")*1,_xlfn._TRO_TRAILING(Artists!A:A),_xlfn._TRO_TRAILING(Artists!B:B)))} -> Daum Frères, Nancy, France | E53: c. 1910 | F53: {=_xlfn.REGEXEXTRACT(E53,"\d{4}")*1} -> 1910 | G53: Blown painted glass | H53: 6 1/4 × 1 3/4 × 1 3/4" (15.9 × 4.4 × 4.4 cm) | I53: Design | J53: Architecture & Design | K53: 28277 | L53: https://www.moma.org/collection/works/3277 | M53: https://www.moma.org/media/W1siZiIsIjIxMTA0NSJdLFsicCIsImNvbnZlcnQiLCItcmVzaXplIDEwMjR4MTAyNFx1MDAzZSJdXQ.jpg?sha=56c0cd5b3f0407f9 | N53: Floor 5, 501
A54: 3279 | B54: Bud Vase | C54: 9682 | D54: {=_xlfn.TEXTJOIN(",",TRUE,_xlfn.XLOOKUP(_xlfn.TEXTSPLIT(C54,",")*1,_xlfn._TRO_TRAILING(Artists!A:A),_xlfn._TRO_TRAILING(Artists!B:B)))} -> Daum Frères, Nancy, France | E54: c. 1910 | F54: {=_xlfn.REGEXEXTRACT(E54,"\d{4}")*1} -> 1910 | G54: Painted glass | H54: 6 × 2 × 2" (15.2 × 5.1 × 5.1 cm) | I54: Design | J54: Architecture & Design | K54: 28277 | L54: https://www.moma.org/collection/works/3279 | M54: https://www.moma.org/media/W1siZiIsIjIxMTA0OSJdLFsicCIsImNvbnZlcnQiLCItcmVzaXplIDEwMjR4MTAyNFx1MDAzZSJdXQ.jpg?sha=9a263074322c30ce | N54: Floor 5, 501
A55: 3281 | B55: Bud Vase | C55: 9682 | D55: {=_xlfn.TEXTJOIN(",",TRUE,_xlfn.XLOOKUP(_xlfn.TEXTSPLIT(C55,",")*1,_xlfn._TRO_TRAILING(Artists!A:A),_xlfn._TRO_TRAILING(Artists!B:B)))} -> Daum Frères, Nancy, France | E55: c. 1910 | F55: {=_xlfn.REGEXEXTRACT(E55,"\d{4}")*1} -> 1910 | G55: Painted glass | H55: 6 5/8 × 2 × 2" (16.8 × 5.1 × 5.1 cm) | I55: Design | J55: Architecture & Design | K55: 28277 | L55: https://www.moma.org/collection/works/3281 | M55: https://www.moma.org/media/W1siZiIsIjIxMTA1MiJdLFsicCIsImNvbnZlcnQiLCItcmVzaXplIDEwMjR4MTAyNFx1MDAzZSJdXQ.jpg?sha=8badf08b3bf9bd3a | N55: Floor 5, 501
A56: 3283 | B56: Bud Vase | C56: 9682 | D56: {=_xlfn.TEXTJOIN(",",TRUE,_xlfn.XLOOKUP(_xlfn.TEXTSPLIT(C56,",")*1,_xlfn._TRO_TRAILING(Artists!A:A),_xlfn._TRO_TRAILING(Artists!B:B)))} -> Daum Frères, Nancy, France | E56: c. 1910 | F56: {=_xlfn.REGEXEXTRACT(E56,"\d{4}")*1} -> 1910 | G56: Blown painted glass | H56: 6 1/4 × 1 7/8 × 1 7/8" (15.9 × 4.8 × 4.8 cm) | I56: Design | J56: Architecture & Design | K56: 28277 | L56: https://www.moma.org/collection/works/3283 | M56: https://www.moma.org/media/W1siZiIsIjIxMTA1OCJdLFsicCIsImNvbnZlcnQiLCItcmVzaXplIDEwMjR4MTAyNFx1MDAzZSJdXQ.jpg?sha=63284f1d21d21b51 | N56: Floor 5, 501
A57: 3285 | B57: Bud Vase | C57: 9682 | D57: {=_xlfn.TEXTJOIN(",",TRUE,_xlfn.XLOOKUP(_xlfn.TEXTSPLIT(C57,",")*1,_xlfn._TRO_TRAILING(Artists!A:A),_xlfn._TRO_TRAILING(Artists!B:B)))} -> Daum Frères, Nancy, France | E57: c. 1910 | F57: {=_xlfn.REGEXEXTRACT(E57,"\d{4}")*1} -> 1910 | G57: Blown painted glass | H57: 6 1/4 × 2 1/8 × 2 1/8" (15.9 × 5.4 × 5.4 cm) | I57: Design | J57: Architecture & Design | K57: 28277 | L57: https://www.moma.org/collection/works/3285 | M57: https://www.moma.org/media/W1siZiIsIjIxMTA2MCJdLFsicCIsImNvbnZlcnQiLCItcmVzaXplIDEwMjR4MTAyNFx1MDAzZSJdXQ.jpg?sha=cd5c1a2d248498ea | N57: Floor 5, 501
A58: 3287 | B58: Bud Vase | C58: 9682 | D58: {=_xlfn.TEXTJOIN(",",TRUE,_xlfn.XLOOKUP(_xlfn.TEXTSPLIT(C58,",")*1,_xlfn._TRO_TRAILING(Artists!A:A),_xlfn._TRO_TRAILING(Artists!B:B)))} -> Daum Frères, Nancy, France | E58: c. 1910 | F58: {=_xlfn.REGEXEXTRACT(E58,"\d{4}")*1} -> 1910 | G58: Blown painted glass | H58: 6 × 2 × 2" (15.2 × 5.1 × 5.1 cm) | I58: Design | J58: Architecture & Design | K58: 28277 | L58: https://www.moma.org/collection/works/3287 | M58: https://www.moma.org/media/W1siZiIsIjIyOTI1OCJdLFsicCIsImNvbnZlcnQiLCItcmVzaXplIDEwMjR4MTAyNFx1MDAzZSJdXQ.jpg?sha=42e3bbf20bda5fa4 | N58: Floor 5, 501
... A61: 3293 | B61: Bud Vase | C61: 9682 | D61: {=_xlfn.TEXTJOIN(",",TRUE,_xlfn.XLOOKUP(_xlfn.TEXTSPLIT(C61,",")*1,_xlfn._TRO_TRAILING(Artists!A:A),_xlfn._TRO_TRAILING(Artists!B:B)))} -> Daum Frères, Nancy, France | E61: c. 1910 | F61: {=_xlfn.REGEXEXTRACT(E61,"\d{4}")*1} -> 1910 | G61: Blown painted glass | H61: 6 3/8 × 2 × 2" (16.2 × 5.1 × 5.1 cm) | I61: Design | J61: Architecture & Design | K61: 28277 | L61: https://www.moma.org/collection/works/3293 | M61: https://www.moma.org/media/W1siZiIsIjIxMTA3MCJdLFsicCIsImNvbnZlcnQiLCItcmVzaXplIDEwMjR4MTAyNFx1MDAzZSJdXQ.jpg?sha=097194eaa5166df5 | N61: Floor 5, 501
A62: 3429 | B62: Crinkle Super Bag Vase K-2 | C62: 3207 | D62: {=_xlfn.TEXTJOIN(",",TRUE,_xlfn.XLOOKUP(_xlfn.TEXTSPLIT(C62,",")*1,_xlfn._TRO_TRAILING(Artists!A:A),_xlfn._TRO_TRAILING(Artists!B:B)))} -> Makoto Komatsu | E62: 1974 | F62: {=_xlfn.REGEXEXTRACT(E62,"\d{4}")*1} -> 1974 | G62: Glazed cast porcelain | H62: 9 7/8 x 7 1/4 x 3 7/16" (25.1 x 18.4 x 8.7 cm) | I62: Design | J62: Architecture & Design | K62: 30251 | L62: https://www.moma.org/collection/works/3429 | M62: https://www.moma.org/media/W1siZiIsIjUyMTQzOCJdLFsicCIsImNvbnZlcnQiLCItcmVzaXplIDEwMjR4MTAyNFx1MDAzZSJdXQ.jpg?sha=850264ab9a249a8d | N62: Floor 1, 1 South
A63: 3431 | B63: Sitzmaschine chair with adjustable back (model 670) | C63: 2694 | D63: {=_xlfn.TEXTJOIN(",",TRUE,_xlfn.XLOOKUP(_xlfn.TEXTSPLIT(C63,",")*1,_xlfn._TRO_TRAILING(Artists!A:A),_xlfn._TRO_TRAILING(Artists!B:B)))} -> Josef Hoffmann | E63: c. 1905 | F63: {=_xlfn.REGEXEXTRACT(E63,"\d{4}")*1} -> 1905 | G63: Bent beechwood with sycamore panels | H63: 43 1/2 x 28 1/4 x 32" (110.5 x 71.8 x 81.3 cm)_x000D_ | I63: Design | J63: Architecture & Design | K63: 34550 | L63: https://www.moma.org/collection/works/3431 | M63: https://www.moma.org/media/W1siZiIsIjIxMTE3MSJdLFsicCIsImNvbnZlcnQiLCItcmVzaXplIDEwMjR4MTAyNFx1MDAzZSJdXQ.jpg?sha=29d70c5763c98fd1 | N63: Floor 5, 504
A64: 3462 | B64: Wine goblet | C64: 4749 | D64: {=_xlfn.TEXTJOIN(",",TRUE,_xlfn.XLOOKUP(_xlfn.TEXTSPLIT(C64,",")*1,_xlfn._TRO_TRAILING(Artists!A:A),_xlfn._TRO_TRAILING(Artists!B:B)))} -> Otto Prutscher | E64: c. 1910 | F64: {=_xlfn.REGEXEXTRACT(E64,"\d{4}")*1} -> 1910 | G64: Flashed and cut glass | H64: 8 1/2 x 3 7/16" (21.6 x 8.8 cm) | I64: Design | J64: Architecture & Design | K64: 31369 | L64: https://www.moma.org/collection/works/3462 | M64: https://www.moma.org/media/W1siZiIsIjIxMTE5NiJdLFsicCIsImNvbnZlcnQiLCItcmVzaXplIDEwMjR4MTAyNFx1MDAzZSJdXQ.jpg?sha=32fead6a5589c548 | N64: Floor 5, 504
A65: 3477 | B65: Zig-Zag Chair | C65: 4922 | D65: {=_xlfn.TEXTJOIN(",",TRUE,_xlfn.XLOOKUP(_xlfn.TEXTSPLIT(C65,",")*1,_xlfn._TRO_TRAILING(Artists!A:A),_xlfn._TRO_TRAILING(Artists!B:B)))} -> Gerrit Rietveld | E65: 1934 | F65: {=_xlfn.REGEXEXTRACT(E65,"\d{4}")*1} -> 1934 | G65: Oak and brass fittings | H65: 29 1/2 x 14 1/2 x 17 1/2" (75 x 36.8 x 44.5 cm), seat h. 16" (40.6 cm) | I65: Design | J65: Architecture & Design | K65: 32469 | L65: https://www.moma.org/collection/works/3477 | M65: https://www.moma.org/media/W1siZiIsIjIyOTUzNCJdLFsicCIsImNvbnZlcnQiLCItcmVzaXplIDEwMjR4MTAyNFx1MDAzZSJdXQ.jpg?sha=b2dbf1d68149c2e3 | N65: Floor 1, 1 South
A66: 3598 | B66: Coffee and Tea Box for the Dutch company Van Nelle | C66: 6971 | D66: {=_xlfn.TEXTJOIN(",",TRUE,_xlfn.XLOOKUP(_xlfn.TEXTSPLIT(C66,",")*1,_xlfn._TRO_TRAILING(Artists!A:A),_xlfn._TRO_TRAILING(Artists!B:B)))} -> Jacob Jongert | E66: 1928–1930 | F66: {=_xlfn.REGEXEXTRACT(E66,"\d{4}")*1} -> 1928 | G66: Printed tin | H66: 14 1/2 x 16 15/16 x 11 1/4" (36.8 x 43 x 28.6 cm) | I66: Design | J66: Architecture & Design | K66: 33898 | L66: https://www.moma.org/collection/works/3598 | M66: https://www.moma.org/media/W1siZiIsIjIyOTY1NyJdLFsicCIsImNvbnZlcnQiLCItcmVzaXplIDEwMjR4MTAyNFx1MDAzZSJdXQ.jpg?sha=1712876c115a84c2 | N66: Floor 5, 511
A67: 3753 | B67: Vase | C67: 2694 | D67: {=_xlfn.TEXTJOIN(",",TRUE,_xlfn.XLOOKUP(_xlfn.TEXTSPLIT(C67,",")*1,_xlfn._TRO_TRAILING(Artists!A:A),_xlfn._TRO_TRAILING(Artists!B:B)))} -> Josef Hoffmann | E67: c. 1905 | F67: {=_xlfn.REGEXEXTRACT(E67,"\d{4}")*1} -> 1905 | G67: Painted perforated metal | H67: 4 1/4 x 3 1/8 x 3 1/8" (10.8 x 8 x 8 cm) | I67: Design | J67: Architecture & Design | K67: 32469 | L67: https://www.moma.org/collection/works/3753 | M67: https://www.moma.org/media/W1siZiIsIjUyNzEyNyJdLFsicCIsImNvbnZlcnQiLCItcmVzaXplIDEwMjR4MTAyNFx1MDAzZSJdXQ.jpg?sha=3e15f584000b3f46 | N67: Floor 5, 504
A68: 3758 | B68: Good Grips Peeler | C68: 10725 | D68: {=_xlfn.TEXTJOIN(",",TRUE,_xlfn.XLOOKUP(_xlfn.TEXTSPLIT(C68,",")*1,_xlfn._TRO_TRAILING(Artists!A:A),_xlfn._TRO_TRAILING(Artists!B:B)))} -> Smart Design, New York | E68: 1989 | F68: {=_xlfn.REGEXEXTRACT(E68,"\d{4}")*1} -> 1989 | G68: Stainless steel and rubber | H68: 7 × 1 3/8 × 1" (17.8 × 3.5 × 2.5 cm) | I68: Design | J68: Architecture & Design | K68: 34598 | L68: https://www.moma.org/collection/works/3758 | M68: https://www.moma.org/media/W1siZiIsIjIxMTI2MSJdLFsicCIsImNvbnZlcnQiLCItcmVzaXplIDEwMjR4MTAyNFx1MDAzZSJdXQ.jpg?sha=eaa3d14dc1eecd76 | N68: Floor 1, 1 South
A69: 3872 | B69: Vase | C69: 4119 | D69: {=_xlfn.TEXTJOIN(",",TRUE,_xlfn.XLOOKUP(_xlfn.TEXTSPLIT(C69,",")*1,_xlfn._TRO_TRAILING(Artists!A:A),_xlfn._TRO_TRAILING(Artists!B:B)))} -> Koloman Moser | E69: 1902 | F69: {=_xlfn.REGEXEXTRACT(E69,"\d{4}")*1} -> 1902 | G69: Glass | H69: 6 x 6 x 6" (15.2 x 15.2 x 15.2 cm) | I69: Design | J69: Architecture & Design | K69: 30453 | L69: https://www.moma.org/collection/works/3872 | M69: https://www.moma.org/media/W1siZiIsIjIxMTQzNyJdLFsicCIsImNvbnZlcnQiLCItcmVzaXplIDEwMjR4MTAyNFx1MDAzZSJdXQ.jpg?sha=20ea4a3a14fd0437 | N69: Floor 5, 504
A70: 3915 | B70: Scissors | C70: 5565 | D70: {=_xlfn.TEXTJOIN(",",TRUE,_xlfn.XLOOKUP(_xlfn.TEXTSPLIT(C70,",")*1,_xlfn._TRO_TRAILING(Artists!A:A),_xlfn._TRO_TRAILING(Artists!B:B)))} -> Alan Spigelman | E70: 1980 | F70: {=_xlfn.REGEXEXTRACT(E70,"\d{4}")*1} -> 1980 | G70: Epoxy-coated stainless steel and plastic | H70: 7 3/16 x 2 9/16" (18.2 x 6.5 cm) | I70: Design | J70: Architecture & Design | K70: 30453 | L70: https://www.moma.org/collection/works/3915 | M70: https://www.moma.org/media/W1siZiIsIjIxMTQ1NiJdLFsicCIsImNvbnZlcnQiLCItcmVzaXplIDEwMjR4MTAyNFx1MDAzZSJdXQ.jpg?sha=ecd2d3f93b60160f | N70: Floor 1, 1 South
A71: 3985 | B71: Screen | C71: 2313 | D71: {=_xlfn.TEXTJOIN(",",TRUE,_xlfn.XLOOKUP(_xlfn.TEXTSPLIT(C71,",")*1,_xlfn._TRO_TRAILING(Artists!A:A),_xlfn._TRO_TRAILING(Artists!B:B)))} -> Eileen Gray | E71: 1922 | F71: {=_xlfn.REGEXEXTRACT(E71,"\d{4}")*1} -> 1922 | G71: Lacquered wood and metal rods | H71: 74 1/2 x 53 1/2 x 3/4" (189.2 x 135.9 x 1.9 cm) | I71: Design | J71: Architecture & Design | K71: 28760 | L71: https://www.moma.org/collection/works/3985 | M71: https://www.moma.org/media/W1siZiIsIjUyMDM2NSJdLFsicCIsImNvbnZlcnQiLCItcmVzaXplIDEwMjR4MTAyNFx1MDAzZSJdXQ.jpg?sha=a317a8ebd8d00171 | N71: Floor 5, 513
A72: 4017 | B72: Bar Tools | C72: 5707 | D72: {=_xlfn.TEXTJOIN(",",TRUE,_xlfn.XLOOKUP(_xlfn.TEXTSPLIT(C72,",")*1,_xlfn._TRO_TRAILING(Artists!A:A),_xlfn._TRO_TRAILING(Artists!B:B)))} -> Studio Opi | E72: 1969 | F72: {=_xlfn.REGEXEXTRACT(E72,"\d{4}")*1} -> 1969 | G72: Stainless steel | H72: .1 (fork): h. 8 1/4" (21 cm)_x000D_ .2 (mixer): h. 8 1/4" (21 cm)_x000D_ .3 (ice tongs): h. 8 1/4" (21 cm)_x000D_ .4 (knife): h. 8 1/4" (21 cm)_x000D_ .5 (can perforator): h. 6 1/4" (15.9 cm)_x000D_ .6 (bottle opener): h. 6 1/4" (15.9 cm) | I72: Design | J72: Architecture & Design | K72: 25877 | L72: https://www.moma.org/collection/works/4017 | M72: https://www.moma.org/media/W1siZiIsIjIxMTUwOCJdLFsicCIsImNvbnZlcnQiLCItcmVzaXplIDEwMjR4MTAyNFx1MDAzZSJdXQ.jpg?sha=8217acae8abf8624 | N72: Floor 1, 1 South
A73: 4023 | B73: Armchair | C73: 6210 | D73: {=_xlfn.TEXTJOIN(",",TRUE,_xlfn.XLOOKUP(_xlfn.TEXTSPLIT(C73,",")*1,_xlfn._TRO_TRAILING(Artists!A:A),_xlfn._TRO_TRAILING(Artists!B:B)))} -> Otto Wagner | E73: 1902 | F73: {=_xlfn.REGEXEXTRACT(E73,"\d{4}")*1} -> 1902 | G73: Bent beechwood and aluminum | H73: 30 7/8 x 22 1/4 x 20 1/4" (78.5 x 56.5 x 51.5 cm), seat h. 18 5/8" (47.3 cm) | I73: Design | J73: Architecture & Design | K73: 28760 | L73: https://www.moma.org/collection/works/4023 | M73: https://www.moma.org/media/W1siZiIsIjIyOTgzNyJdLFsicCIsImNvbnZlcnQiLCItcmVzaXplIDEwMjR4MTAyNFx1MDAzZSJdXQ.jpg?sha=022d146ca9d75fd8 | N73: Floor 5, 504
A74: 4026 | B74: Stool | C74: 6210 | D74: {=_xlfn.TEXTJOIN(",",TRUE,_xlfn.XLOOKUP(_xlfn.TEXTSPLIT(C74,",")*1,_xlfn._TRO_TRAILING(Artists!A:A),_xlfn._TRO_TRAILING(Artists!B:B)))} -> Otto Wagner | E74: 1904 | F74: {=_xlfn.REGEXEXTRACT(E74,"\d{4}")*1} -> 1904 | G74: Bent beechwood, molded plywood, and aluminum | H74: 18 1/2 x 16 x 16" (47 x 40.6 x 40.6 cm) | I74: Design | J74: Architecture & Design | K74: 28760 | L74: https://www.moma.org/collection/works/4026 | M74: https://www.moma.org/media/W1siZiIsIjUyMDM2NyJdLFsicCIsImNvbnZlcnQiLCItcmVzaXplIDEwMjR4MTAyNFx1MDAzZSJdXQ.jpg?sha=d4986e9ca0b6dc4c | N74: Floor 5, 504
A75: 4044 | B75: Red Blue Chair | C75: 4922 | D75: {=_xlfn.TEXTJOIN(",",TRUE,_xlfn.XLOOKUP(_xlfn.TEXTSPLIT(C75,",")*1,_xlfn._TRO_TRAILING(Artists!A:A),_xlfn._TRO_TRAILING(Artists!B:B)))} -> Gerrit Rietveld | E75: 1918–1923 | F75: {=_xlfn.REGEXEXTRACT(E75,"\d{4}")*1} -> 1918 | G75: Painted wood | H75: 34 1/8 x 26 x 33" (86.7 x 66 x 83.8 cm), seat h. 13" (33 cm) | I75: Design | J75: Architecture & Design | K75: 19667 | L75: https://www.moma.org/collection/works/4044 | M75: https://www.moma.org/media/W1siZiIsIjQwMjU2OSJdLFsicCIsImNvbnZlcnQiLCItcmVzaXplIDEwMjR4MTAyNFx1MDAzZSJdXQ.jpg?sha=e7e6d212890598a1 | N75: Floor 1, 1 South
A76: 4110 | B76: Goblet | C76: 4749 | D76: {=_xlfn.TEXTJOIN(",",TRUE,_xlfn.XLOOKUP(_xlfn.TEXTSPLIT(C76,",")*1,_xlfn._TRO_TRAILING(Artists!A:A),_xlfn._TRO_TRAILING(Artists!B:B)))} -> Otto Prutscher | E76: c. 1905 | F76: {=_xlfn.REGEXEXTRACT(E76,"\d{4}")*1} -> 1905 | G76: Flashed and hand-painted cut glass | H76: 8 1/8 x 3 1/8" (20.6 x 7.9 cm) | I76: Design | J76: Architecture & Design | K76: 29930 | L76: https://www.moma.org/collection/works/4110 | M76: https://www.moma.org/media/W1siZiIsIjIxMTY2OCJdLFsicCIsImNvbnZlcnQiLCItcmVzaXplIDEwMjR4MTAyNFx1MDAzZSJdXQ.jpg?sha=1eb93e6bcce8e17e | N76: Floor 5, 504
A77: 4334 | B77: Flatware | C77: 2694 | D77: {=_xlfn.TEXTJOIN(",",TRUE,_xlfn.XLOOKUP(_xlfn.TEXTSPLIT(C77,",")*1,_xlfn._TRO_TRAILING(Artists!A:A),_xlfn._TRO_TRAILING(Artists!B:B)))} -> Josef Hoffmann | E77: 1905 | F77: {=_xlfn.REGEXEXTRACT(E77,"\d{4}")*1} -> 1905 | G77: Silver-plate on nickel silver | H77: .1 (large knife): l. 8 1/2" (21.6 cm) _x000D_ .2 (small knife): l. 7 1/4" (18.4 cm) _x000D_ .3 (butter knife): l. 7 1/4" (18.4 cm) _x000D_ .4 (soupspoon): l. 8 1/4" (21 cm) _x000D_ .5 (teaspoon): l. 5 5/8" (14.3 cm) _x000D_ .6 (coffee spoon): l. 4" (10.2 cm) _x000D_ .7 (large fork): l. 8 3/8" (21.3 cm) _x000D_ .8 (small fork): l. 7 1/4" (18.4 cm) _x000D_ .9 (serving fork): l. 10 1/2" (26.7 cm) _x000D_ .10 (serving spoon): l. 10" (25.4 cm) | I77: Design | J77: Architecture & Design | K77: 28457 | L77: https://www.moma.org/collection/works/4334 | M77: https://www.moma.org/media/W1siZiIsIjUyMDM5MCJdLFsicCIsImNvbnZlcnQiLCItcmVzaXplIDEwMjR4MTAyNFx1MDAzZSJdXQ.jpg?sha=958e1cadfaada0fc | N77: Floor 5, 504
A78: 4339 | B78: Adjustable Table | C78: 2313 | D78: {=_xlfn.TEXTJOIN(",",TRUE,_xlfn.XLOOKUP(_xlfn.TEXTSPLIT(C78,",")*1,_xlfn._TRO_TRAILING(Artists!A:A),_xlfn._TRO_TRAILING(Artists!B:B)))} -> Eileen Gray | E78: Designed 1927 (this example 1976) | F78: {=_xlfn.REGEXEXTRACT(E78,"\d{4}")*1} -> 1927 | G78: Chrome-plated tubular steel, sheet steel, and glass | H78: Dimensions range from a minimum height of 21 1/4" (54 cm) to max height of 36 1/2" (93 cm), diam. 20" (50.8 cm) | I78: Design | J78: Architecture & Design | K78: 28457 | L78: https://www.moma.org/collection/works/4339 | M78: https://www.moma.org/media/W1siZiIsIjIyOTk2MSJdLFsicCIsImNvbnZlcnQiLCItcmVzaXplIDEwMjR4MTAyNFx1MDAzZSJdXQ.jpg?sha=46b1f327991a5475 | N78: Floor 5, 513
A79: 4369 | B79: Barcelona Chair | C79: 7166 | D79: {=_xlfn.TEXTJOIN(",",TRUE,_xlfn.XLOOKUP(_xlfn.TEXTSPLIT(C79,",")*1,_xlfn._TRO_TRAILING(Artists!A:A),_xlfn._TRO_TRAILING(Artists!B:B)))} -> Ludwig Mies van der Rohe | E79: Designed 1929 (this example 1953) | F79: {=_xlfn.REGEXEXTRACT(E79,"\d{4}")*1} -> 1929 | G79: Stainless-steel bars and leather upholstery | H79: 31 x 29 3/8 x 30" (78.7 x 74.6 x 76.2 cm) | I79: Design | J79: Architecture & Design | K79: 19736 | L79: https://www.moma.org/collection/works/4369 | M79: https://www.moma.org/media/W1siZiIsIjIxMTY0MCJdLFsicCIsImNvbnZlcnQiLCItcmVzaXplIDEwMjR4MTAyNFx1MDAzZSJdXQ.jpg?sha=b705f616552d4bd2 | N79: Floor 1, 1 South
A80: 4379 | B80: Vase | C80: 9682 | D80: {=_xlfn.TEXTJOIN(",",TRUE,_xlfn.XLOOKUP(_xlfn.TEXTSPLIT(C80,",")*1,_xlfn._TRO_TRAILING(Artists!A:A),_xlfn._TRO_TRAILING(Artists!B:B)))} -> Daum Frères, Nancy, France | E80: c. 1900 | F80: {=_xlfn.REGEXEXTRACT(E80,"\d{4}")*1} -> 1900 | G80: Painted glass | H80: 23 1/4 × 5 1/2 × 5 1/2" (59.1 × 14 × 14 cm) | I80: Design | J80: Architecture & Design | K80: 21914 | L80: https://www.moma.org/collection/works/4379 | M80: https://www.moma.org/media/W1siZiIsIjU1NjIwNiJdLFsicCIsImNvbnZlcnQiLCItcmVzaXplIDEwMjR4MTAyNFx1MDAzZSJdXQ.jpg?sha=6789d16d8b920e79 | N80: Floor 5, 501
A81: 4401 | B81: Armchair | C81: 159 | D81: {=_xlfn.TEXTJOIN(",",TRUE,_xlfn.XLOOKUP(_xlfn.TEXTSPLIT(C81,",")*1,_xlfn._TRO_TRAILING(Artists!A:A),_xlfn._TRO_TRAILING(Artists!B:B)))} -> Gunnar Aagaard Andersen | E81: 1964 | F81: {=_xlfn.REGEXEXTRACT(E81,"\d{4}")*1} -> 1964 | G81: Poured polyurethane | H81: 29 1/2 x 44 1/4 x 35 1/4" (74.9 x 112.4 x 89.5 cm) | I81: Design | J81: Architecture & Design | K81: 24447 | L81: https://www.moma.org/collection/works/4401 | M81: https://www.moma.org/media/W1siZiIsIjIzMDUxOCJdLFsicCIsImNvbnZlcnQiLCItcmVzaXplIDEwMjR4MTAyNFx1MDAzZSJdXQ.jpg?sha=dd903634a7d1c612 | N81: Floor 4, 417
A82: 4418 | B82: Coat Hangers | C82: 7221 | D82: {=_xlfn.TEXTJOIN(",",TRUE,_xlfn.XLOOKUP(_xlfn.TEXTSPLIT(C82,",")*1,_xlfn._TRO_TRAILING(Artists!A:A),_xlfn._TRO_TRAILING(Artists!B:B)))} -> Roald Steen Hansen | E82: 1974 | F82: {=_xlfn.REGEXEXTRACT(E82,"\d{4}")*1} -> 1974 | G82: Beechwood | H82: .a (coat hanger): 8 11/16 x 16 1/8 x 1 3/16" (22 x 41 x 3 cm)_x000D_ .b (support, wall button): 2 3/4 x 3 1/8" (7 x 7.9 cm) | I82: Design | J82: Architecture & Design | K82: 30650 | L82: https://www.moma.org/collection/works/4418 | M82: https://www.moma.org/media/W1siZiIsIjIxMTg2MiJdLFsicCIsImNvbnZlcnQiLCItcmVzaXplIDEwMjR4MTAyNFx1MDAzZSJdXQ.jpg?sha=ba482d5768de797e | N82: Floor 1, 1 South
A83: 4443 | B83: Salt and Pepper Shakers | C83: 6208 | D83: {=_xlfn.TEXTJOIN(",",TRUE,_xlfn.XLOOKUP(_xlfn.TEXTSPLIT(C83,",")*1,_xlfn._TRO_TRAILING(Artists!A:A),_xlfn._TRO_TRAILING(Artists!B:B)))} -> Wilhelm Wagenfeld | E83: 1952-53 | F83: {=_xlfn.REGEXEXTRACT(E83,"\d{4}")*1} -> 1952 | G83: Stainless steel and glass | H83: Each: 2 1/2 x 2" (6.3 x 5.1 cm) | I83: Design | J83: Architecture & Design | K83: 30650 | L83: https://www.moma.org/collection/works/4443 | M83: https://www.moma.org/media/W1siZiIsIjIxMTg3OSJdLFsicCIsImNvbnZlcnQiLCItcmVzaXplIDEwMjR4MTAyNFx1MDAzZSJdXQ.jpg?sha=300632c5609de936 | N83: Floor 1, 1 South
A84: 4444 | B84: Kryptonite 4 Bike Lock | C84: 6543, 7217 | D84: {=_xlfn.TEXTJOIN(",",TRUE,_xlfn.XLOOKUP(_xlfn.TEXTSPLIT(C84,",")*1,_xlfn._TRO_TRAILING(Artists!A:A),_xlfn._TRO_TRAILING(Artists!B:B)))} -> Michael S. Zane,Peter L. Zane | E84: 1976 | F84: {=_xlfn.REGEXEXTRACT(E84,"\d{4}")*1} -> 1976 | G84: Vinyl-coated zinc and nickel-plated steel | H84: Each: 10 5/8 x 7 1/2" (27 x 19.1 cm) | I84: Design | J84: Architecture & Design | K84: 30650 | L84: https://www.moma.org/collection/works/4444 | M84: https://www.moma.org/media/W1siZiIsIjIxMTg4MSJdLFsicCIsImNvbnZlcnQiLCItcmVzaXplIDEwMjR4MTAyNFx1MDAzZSJdXQ.jpg?sha=a9611fee4ae4ff92 | N84: Floor 1, 1 South
A85: 4457 | B85: Candleholder | C85: 6356 | D85: {=_xlfn.TEXTJOIN(",",TRUE,_xlfn.XLOOKUP(_xlfn.TEXTSPLIT(C85,",")*1,_xlfn._TRO_TRAILING(Artists!A:A),_xlfn._TRO_TRAILING(Artists!B:B)))} -> Metall-Arbeit Wiener Werkstätte | E85: c. 1903-04 | F85: {=_xlfn.REGEXEXTRACT(E85,"\d{4}")*1} -> 1903 | G85: Hammered silver | H85: 7 5/8 x 6 3/8" (19.4 x 16.2 cm) | I85: Design | J85: Architecture & Design | K85: 15311 | L85: https://www.moma.org/collection/works/4457 | M85: https://www.moma.org/media/W1siZiIsIjIzMDU1NSJdLFsicCIsImNvbnZlcnQiLCItcmVzaXplIDEwMjR4MTAyNFx1MDAzZSJdXQ.jpg?sha=727e58f4d60c737b | N85: Floor 5, 504
A86: 4597 | B86: Chronotime Clock | C86: 3743 | D86: {=_xlfn.TEXTJOIN(",",TRUE,_xlfn.XLOOKUP(_xlfn.TEXTSPLIT(C86,",")*1,_xlfn._TRO_TRAILING(Artists!A:A),_xlfn._TRO_TRAILING(Artists!B:B)))} -> Pio Manzù | E86: 1968 | F86: {=_xlfn.REGEXEXTRACT(E86,"\d{4}")*1} -> 1968 | G86: ABS polymer casing and metal parts | H86: Each: 2 5/8 x 2 3/4" (6.7 x 7 cm) | I86: Design | J86: Architecture & Design | K86: 25538 | L86: https://www.moma.org/collection/works/4597 | M86: https://www.moma.org/media/W1siZiIsIjIzMDAxOCJdLFsicCIsImNvbnZlcnQiLCItcmVzaXplIDEwMjR4MTAyNFx1MDAzZSJdXQ.jpg?sha=2cd266d22ae269d4 | N86: Floor 1, 1 South
A87: 4635 | B87: Stacking Tumblers | C87: 3822 | D87: {=_xlfn.TEXTJOIN(",",TRUE,_xlfn.XLOOKUP(_xlfn.TEXTSPLIT(C87,",")*1,_xlfn._TRO_TRAILING(Artists!A:A),_xlfn._TRO_TRAILING(Artists!B:B)))} -> Luigi Massoni | E87: 1967 | F87: {=_xlfn.REGEXEXTRACT(E87,"\d{4}")*1} -> 1967 | G87: Acrylic | H87: Each: 2 15/16 x 2 9/16" (7.5 x 6.5 cm) | I87: Design | J87: Architecture & Design | K87: 25118 | L87: https://www.moma.org/collection/works/4635 | M87: https://www.moma.org/media/W1siZiIsIjUxOTU1OCJdLFsicCIsImNvbnZlcnQiLCItcmVzaXplIDEwMjR4MTAyNFx1MDAzZSJdXQ.jpg?sha=04c6bbe652c9cb5f | N87: Floor 1, 1 South
A88: 4729 | B88: Lounge Chair | C88: 8435 | D88: {=_xlfn.TEXTJOIN(",",TRUE,_xlfn.XLOOKUP(_xlfn.TEXTSPLIT(C88,",")*1,_xlfn._TRO_TRAILING(Artists!A:A),_xlfn._TRO_TRAILING(Artists!B:B)))} -> Gerald Summers | E88: 1934 | F88: {=_xlfn.REGEXEXTRACT(E88,"\d{4}")*1} -> 1934 | G88: Bent birch plywood with pigmented lacquer | H88: 29 5/8 x 23 1/2 x 35" (75.2 x 59.7 x 88.9 cm) | I88: Design | J88: Architecture & Design | K88: 36871 | L88: https://www.moma.org/collection/works/4729 | M88: https://www.moma.org/media/W1siZiIsIjIzMDE5MyJdLFsicCIsImNvbnZlcnQiLCItcmVzaXplIDEwMjR4MTAyNFx1MDAzZSJdXQ.jpg?sha=f50536dfb66d9f2e | N88: Floor 1, 1 South
A89: 5376 | B89: Poster for the Kunstschau exhibition, Vienna | C89: 3585 | D89: {=_xlfn.TEXTJOIN(",",TRUE,_xlfn.XLOOKUP(_xlfn.TEXTSPLIT(C89,",")*1,_xlfn._TRO_TRAILING(Artists!A:A),_xlfn._TRO_TRAILING(Artists!B:B)))} -> Berthold Löffler | E89: 1908 | F89: {=_xlfn.REGEXEXTRACT(E89,"\d{4}")*1} -> 1908 | G89: Lithograph | H89: 14 3/8 x 19 1/2" (37.5 x 49.5 cm) | I89: Design | J89: Architecture & Design | K89: 32260 | L89: https://www.moma.org/collection/works/5376 | M89: https://www.moma.org/media/W1siZiIsIjIxMDUwNCJdLFsicCIsImNvbnZlcnQiLCItcmVzaXplIDEwMjR4MTAyNFx1MDAzZSJdXQ.jpg?sha=3029e91170ae38c9 | N89: Floor 5, 504
A90: 5684 | B90: Poster for the First Secession Exhibition (censored version) (1. Kunstausstellung Secession) | C90: 3147 | D90: {=_xlfn.TEXTJOIN(",",TRUE,_xlfn.XLOOKUP(_xlfn.TEXTSPLIT(C90,",")*1,_xlfn._TRO_TRAILING(Artists!A:A),_xlfn._TRO_TRAILING(Artists!B:B)))} -> Gustav Klimt | E90: 1898 | F90: {=_xlfn.REGEXEXTRACT(E90,"\d{4}")*1} -> 1898 | G90: Lithograph | H90: 25 x 18 7/16" (63.5 x 46.9 cm) | I90: Design | J90: Architecture & Design | K90: 24904 | L90: https://www.moma.org/collection/works/5684 | M90: https://www.moma.org/media/W1siZiIsIjE3MDI1NCJdLFsicCIsImNvbnZlcnQiLCItcmVzaXplIDEwMjR4MTAyNFx1MDAzZSJdXQ.jpg?sha=c6ccaa5c234495fd | N90: Floor 5, 504
A91: 5724 | B91: Radio - Rural Electrification Administration | C91: 409 | D91: {=_xlfn.TEXTJOIN(",",TRUE,_xlfn.XLOOKUP(_xlfn.TEXTSPLIT(C91,",")*1,_xlfn._TRO_TRAILING(Artists!A:A),_xlfn._TRO_TRAILING(Artists!B:B)))} -> Lester Beall | E91: 1937 | F91: {=_xlfn.REGEXEXTRACT(E91,"\d{4}")*1} -> 1937 | G91: Silkscreen | H91: 40 1/4 x 30" (102 x 76.2 cm) | I91: Design | J91: Architecture & Design | K91: 13696 | L91: https://www.moma.org/collection/works/5724 | M91: https://www.moma.org/media/W1siZiIsIjUxNzI5MiJdLFsicCIsImNvbnZlcnQiLCItcmVzaXplIDEwMjR4MTAyNFx1MDAzZSJdXQ.jpg?sha=505c68eea17d4cac | N91: Floor 5, 519
A92: 5745 | B92: Running Water - Rural Electrification Administration | C92: 409 | D92: {=_xlfn.TEXTJOIN(",",TRUE,_xlfn.XLOOKUP(_xlfn.TEXTSPLIT(C92,",")*1,_xlfn._TRO_TRAILING(Artists!A:A),_xlfn._TRO_TRAILING(Artists!B:B)))} -> Lester Beall | E92: 1937 | F92: {=_xlfn.REGEXEXTRACT(E92,"\d{4}")*1} -> 1937 | G92: Silkscreen | H92: 40 x 30" (101.6 x 76.2 cm) | I92: Design | J92: Architecture & Design | K92: 13696 | L92: https://www.moma.org/collection/works/5745 | M92: https://www.moma.org/media/W1siZiIsIjIxMDc1NSJdLFsicCIsImNvbnZlcnQiLCItcmVzaXplIDEwMjR4MTAyNFx1MDAzZSJdXQ.jpg?sha=e7249b0a9758edf8 | N92: Floor 5, 519
A93: 6706 | B93: Contact With the World, Use the Telephone | C93: 3020 | D93: {=_xlfn.TEXTJOIN(",",TRUE,_xlfn.XLOOKUP(_xlfn.TEXTSPLIT(C93,",")*1,_xlfn._TRO_TRAILING(Artists!A:A),_xlfn._TRO_TRAILING(Artists!B:B)))} -> E. McKnight Kauffer | E93: 1934 | F93: {=_xlfn.REGEXEXTRACT(E93,"\d{4}")*1} -> 1934 | G93: Lithograph | H93: 29 7/8 x 19 5/8" (75.9 x 49.8 cm) | I93: Design | J93: Architecture & Design | K93: 14387 | L93: https://www.moma.org/collection/works/6706 | M93: https://www.moma.org/media/W1siZiIsIjUxNzAyOCJdLFsicCIsImNvbnZlcnQiLCItcmVzaXplIDEwMjR4MTAyNFx1MDAzZSJdXQ.jpg?sha=612588e3a9065533 | N93: Floor 5, 519
A94: 7306 | B94: Secession Plakat Ausstellung (Secession Poster Exhibition) | C94: 2507 | D94: {=_xlfn.TEXTJOIN(",",TRUE,_xlfn.XLOOKUP(_xlfn.TEXTSPLIT(C94,",")*1,_xlfn._TRO_TRAILING(Artists!A:A),_xlfn._TRO_TRAILING(Artists!B:B)))} -> Richard Harlfinger | E94: 1912 | F94: {=_xlfn.REGEXEXTRACT(E94,"\d{4}")*1} -> 1912 | G94: Lithograph | H94: 24 3/4 x 18 1/2" (62.8 x 46.9 cm) | I94: Design | J94: Architecture & Design | K94: 30453 | L94: https://www.moma.org/collection/works/7306 | M94: https://www.moma.org/media/W1siZiIsIjIxMTU3MyJdLFsicCIsImNvbnZlcnQiLCItcmVzaXplIDEwMjR4MTAyNFx1MDAzZSJdXQ.jpg?sha=47990799a887551c | N94: Floor 5, 504
A95: 10808 | B95: Double page plate (between pages 96 and 97) from Vertogradari Nad Lozami (Gardeners over the Vines) | C95: 2229 | D95: {=_xlfn.TEXTJOIN(",",TRUE,_xlfn.XLOOKUP(_xlfn.TEXTSPLIT(C95,",")*1,_xlfn._TRO_TRAILING(Artists!A:A),_xlfn._TRO_TRAILING(Artists!B:B)))} -> Natalia Goncharova | E95: 1913 | F95: {=_xlfn.REGEXEXTRACT(E95,"\d{4}")*1} -> 1913 | G95: Lithograph from an illustrated book with ten lithographs and two woodcuts | H95: composition (irreg.): 6 5/8 × 8 9/16" (16.8 × 21.8 cm); page (each): 6 15/16 × 4 1/2" (17.7 × 11.4 cm) | I95: Illustrated Book | J95: Drawings & Prints | K95: 28166 | L95: https://www.moma.org/collection/works/10808 | M95: https://www.moma.org/media/W1siZiIsIjQ2MjI3NCJdLFsicCIsImNvbnZlcnQiLCItcmVzaXplIDEwMjR4MTAyNFx1MDAzZSJdXQ.jpg?sha=81bad5a283785c3b | N95: Floor 5, 507
A96: 26720 | B96: Sleeping Woman (Schlafende Frau) (title page) from Die träumenden Knaben (The Dreaming Boys) | C96: 3197 | D96: {=_xlfn.TEXTJOIN(",",TRUE,_xlfn.XLOOKUP(_xlfn.TEXTSPLIT(C96,",")*1,_xlfn._TRO_TRAILING(Artists!A:A),_xlfn._TRO_TRAILING(Artists!B:B)))} -> Oskar Kokoschka | E96: 1917 (executed 1907-08) | F96: {=_xlfn.REGEXEXTRACT(E96,"\d{4}")*1} -> 1917 | G96: Photolithograph from an illustrated book with eight photolithographs and three line block reproductions | H96: composition: 9 7/16 x 8 7/8" (24 x 22.5 cm); page: 9 7/16 x 11 9/16" (24 x 29.3 cm) | I96: Illustrated Book | J96: Drawings & Prints | K96: 23656 | L96: https://www.moma.org/collection/works/26720 | M96: https://www.moma.org/media/W1siZiIsIjEyOTUzMSJdLFsicCIsImNvbnZlcnQiLCItcmVzaXplIDEwMjR4MTAyNFx1MDAzZSJdXQ.jpg?sha=48911516ef760993 | N96: Floor 5, 504
A97: 26721 | B97: Die träumenden Knaben (The Dreaming Boys) | C97: 3197 | D97: {=_xlfn.TEXTJOIN(",",TRUE,_xlfn.XLOOKUP(_xlfn.TEXTSPLIT(C97,",")*1,_xlfn._TRO_TRAILING(Artists!A:A),_xlfn._TRO_TRAILING(Artists!B:B)))} -> Oskar Kokoschka | E97: 1917 (prints executed 1907-08) | F97: {=_xlfn.REGEXEXTRACT(E97,"\d{4}")*1} -> 1917 | G97: Illustrated book with eight photolithographs and three line block reproductions | H97: overall: 9 9/16 x 11 11/16 x 3/8" (24.3 x 29.7 x 0.9 cm); page (each): 9 7/16 x 11 9/16" (24 x 29.3 cm); sheet (of composition): 3 7/8 x 2 7/8" (9.8 x 7.3 cm); composition: 3 9/16 x 2 9/16" (9 x 6.5 cm) | I97: Illustrated Book | J97: Drawings & Prints | K97: 23656 | L97: https://www.moma.org/collection/works/26721 | M97: https://www.moma.org/media/W1siZiIsIjEyOTUzMiJdLFsicCIsImNvbnZlcnQiLCItcmVzaXplIDEwMjR4MTAyNFx1MDAzZSJdXQ.jpg?sha=e5640ff7ffedf3c7 | N97: Floor 5, 504
A98: 26722 | B98: The Sailboat (Das Segelschiff) (in-text plate, folio 4) from Die träumenden Knaben (The Dreaming Boys) | C98: 3197 | D98: {=_xlfn.TEXTJOIN(",",TRUE,_xlfn.XLOOKUP(_xlfn.TEXTSPLIT(C98,",")*1,_xlfn._TRO_TRAILING(Artists!A:A),_xlfn._TRO_TRAILING(Artists!B:B)))} -> Oskar Kokoschka | E98: 1917 (executed 1907-08) | F98: {=_xlfn.REGEXEXTRACT(E98,"\d{4}")*1} -> 1917 | G98: Photolithograph from an illustrated book with eight photolithographs and three line block reproductions | H98: composition: 9 7/16 x 9" (24 x 22.9 cm); page: 9 7/16 x 11 9/16" (24 x 29.3 cm) | I98: Illustrated Book | J98: Drawings & Prints | K98: 23656 | L98: https://www.moma.org/collection/works/26722 | M98: https://www.moma.org/media/W1siZiIsIjEyOTUzNiJdLFsicCIsImNvbnZlcnQiLCItcmVzaXplIDEwMjR4MTAyNFx1MDAzZSJdXQ.jpg?sha=5149945fe5cb8b37 | N98: Floor 5, 504
A99: 27170 | B99: Plate (page 61) from Le Poème de l'angle droit (The Poem of the Right Angle) | C99: 3426 | D99: {=_xlfn.TEXTJOIN(",",TRUE,_xlfn.XLOOKUP(_xlfn.TEXTSPLIT(C99,",")*1,_xlfn._TRO_TRAILING(Artists!A:A),_xlfn._TRO_TRAILING(Artists!B:B)))} -> Le Corbusier (Charles-Édouard Jeanneret) | E99: 1947–53, published 1955 | F99: {=_xlfn.REGEXEXTRACT(E99,"\d{4}")*1} -> 1947 | G99: Lithograph from an illustrated book with 121 lithographs, including covers (one with collage) | H99: composition (irreg.): 16 1/4 × 12 1/2" (41.2 × 31.8 cm); page (each): 16 9/16 × 12 11/16" (42 × 32.3 cm) | I99: Illustrated Book | J99: Drawings & Prints | K99: 23656 | L99: https://www.moma.org/collection/works/27170 | M99: https://www.moma.org/media/W1siZiIsIjIzMTYzOCJdLFsicCIsImNvbnZlcnQiLCItcmVzaXplIDEwMjR4MTAyNFx1MDAzZSJdXQ.jpg?sha=529cca49aacafda6 | N99: Floor 4, 417
A100: 28449 | B100: Jazz | C100: 3832 | D100: {=_xlfn.TEXTJOIN(",",TRUE,_xlfn.XLOOKUP(_xlfn.TEXTSPLIT(C100,",")*1,_xlfn._TRO_TRAILING(Artists!A:A),_xlfn._TRO_TRAILING(Artists!B:B)))} -> Henri Matisse | E100: 1943–47, published 1947 | F100: {=_xlfn.REGEXEXTRACT(E100,"\d{4}")*1} -> 1943 | G100: Illustrated book with twenty pochoirs | H100: page (each approx.): 16 5/8 × 12 13/16" (42.2 × 32.5 cm); overall (closed): 16 11/16 × 13 × 1 3/4" (42.4 × 33 × 4.4 cm) | I100: Illustrated Book | J100: Drawings & Prints | K100: 23656 | L100: https://www.moma.org/collection/works/28449 | M100: https://www.moma.org/media/W1siZiIsIjI5MTM3MiJdLFsicCIsImNvbnZlcnQiLCItcmVzaXplIDEwMjR4MTAyNFx1MDAzZSJdXQ.jpg?sha=4ce98e49f13b6b46 | N100: Floor 4, 406
A101: 32973 | B101: Bathers | C101: 1053 | D101: {=_xlfn.TEXTJOIN(",",TRUE,_xlfn.XLOOKUP(_xlfn.TEXTSPLIT(C101,",")*1,_xlfn._TRO_TRAILING(Artists!A:A),_xlfn._TRO_TRAILING(Artists!B:B)))} -> Paul Cézanne | E101: c. 1885-1890 | F101: {=_xlfn.REGEXEXTRACT(E101,"\d{4}")*1} -> 1885 | G101: Watercolor and pencil on paper | H101: 5 x 8 1/8" (12.7 x 20.6 cm) | I101: Drawing | J101: Drawings & Prints | K101: 12685 | L101: https://www.moma.org/collection/works/32973 | M101: https://www.moma.org/media/W1siZiIsIjM0OTg3MSJdLFsicCIsImNvbnZlcnQiLCItcmVzaXplIDEwMjR4MTAyNFx1MDAzZSJdXQ.jpg?sha=53145f1a4ef757df | N101: Floor 2, 2 South
A102: 33075 | B102: Foliage (recto); Study of Trees (verso) | C102: 1053 | D102: {=_xlfn.TEXTJOIN(",",TRUE,_xlfn.XLOOKUP(_xlfn.TEXTSPLIT(C102,",")*1,_xlfn._TRO_TRAILING(Artists!A:A),_xlfn._TRO_TRAILING(Artists!B:B)))} -> Paul Cézanne | E102: 1895 | F102: {=_xlfn.REGEXEXTRACT(E102,"\d{4}")*1} -> 1895 | G102: Watercolor and pencil on paper (recto and verso) | H102: 17 5/8 x 22 3/8" (44.8 x 56.8 cm)_x000D_ | I102: Drawing | J102: Drawings & Prints | K102: 12685 | L102: https://www.moma.org/collection/works/33075 | M102: https://www.moma.org/media/W1siZiIsIjE2OTI3MCJdLFsicCIsImNvbnZlcnQiLCItcmVzaXplIDEwMjR4MTAyNFx1MDAzZSJdXQ.jpg?sha=16f07bc818945b64 | N102: Floor 2, 2 South
...
